{"_default": {"1": {"ewirch": {"issues": [{"url": "https://api.github.com/repos/spring-projects/spring-data-book/issues/22", "title": "jpa examples violate the hashCode()/equals() contract", "body": "Add this line at the end of `com.oreilly.springdata.jpa.core.CustomerRepositoryIntegrationTest.savesCustomerCorrectly()` test:\r\n```\r\nassertTrue(dave.getAddresses().contains(dave.getAddresses().iterator().next()));\r\n```\r\nThe test will fail. Even though every Java developer reading this line will expect the test to pass.\r\n\r\nThis is because the example is implemented in a way that fields which are used for equals/hashCode (`id`) are modified after the object has been added to a `HashSet`.", "reactions": {"url": "https://api.github.com/repos/spring-projects/spring-data-book/issues/22/reactions", "total_count": 0, "+1": 0, "-1": 0, "laugh": 0, "hooray": 0, "confused": 0, "heart": 0}, "author_association": "NONE"}], "commits": [], "pull_requests": [], "issue_comments": [], "commit_comments": [], "review_comments": []}, "funmler": {"issues": [{"url": "https://api.github.com/repos/spring-projects/spring-data-book/issues/21", "title": "Example Tests fail", "body": "[trace.txt](https://github.com/spring-projects/spring-data-book/files/190111/trace.txt)\nHi was trying to get the example to run and had a few failures.\n`\n\n> git clone https://github.com/SpringSource/spring-data-book.git\n> cd spring-data-book\n> mvn clean package\n\n[INFO] Scanning for projects...\n[INFO] ------------------------------------------------------------------------\n[INFO] Reactor Build Order:\n[INFO] \n[INFO] Spring Data Book\n[INFO] Spring Data Book - JPA\n[INFO] Spring Data Book - MongoDB\n[INFO] Spring Data Book - Querydsl\n[INFO] Spring Data Book - Neo4J\n[INFO] Spring Data Book - JDBC\n[INFO] Spring Data Book - Redis\n[INFO] Spring Data Book - GemFire\n[INFO] Spring Data Book - REST exporter\n[INFO]  \n[INFO] ------------------------------------------------------------------------\n[INFO] Building Spring Data Book 1.0.0.BUILD-SNAPSHOT\n[INFO] ------------------------------------------------------------------------\n[INFO] \n[INFO] --- maven-clean-plugin:2.5:clean (default-clean) @ spring-data-book ---\n[INFO]  \n[INFO] ------------------------------------------------------------------------\n[INFO] Building Spring Data Book - JPA 1.0.0.BUILD-SNAPSHOT\n[INFO] ------------------------------------------------------------------------\n[INFO] \n[INFO] --- maven-clean-plugin:2.5:clean (default-clean) @ spring-data-book-jpa ---\n[INFO] \n[INFO] --- apt-maven-plugin:1.0.8:process (default) @ spring-data-book-jpa ---\n[INFO] \n[INFO] --- maven-resources-plugin:2.6:resources (default-resources) @ spring-data-book-jpa ---\n[INFO] Using 'UTF-8' encoding to copy filtered resources.\n[INFO] Copying 1 resource\n[INFO] \n[INFO] --- maven-compiler-plugin:3.0:compile (default-compile) @ spring-data-book-jpa ---\n[INFO] Changes detected - recompiling the module!\n[INFO] Compiling 21 source files to /home/joe/dev/spring-data-book/jpa/target/classes\n[WARNING] /home/joe/dev/spring-data-book/jpa/target/generated-sources/com/oreilly/springdata/jpa/core/QProduct.java: Some input files use unchecked or unsafe operations.\n[WARNING] /home/joe/dev/spring-data-book/jpa/target/generated-sources/com/oreilly/springdata/jpa/core/QProduct.java: Recompile with -Xlint:unchecked for details.\n[INFO] \n[INFO] --- maven-resources-plugin:2.6:testResources (default-testResources) @ spring-data-book-jpa ---\n[INFO] Using 'UTF-8' encoding to copy filtered resources.\n[INFO] Copying 2 resources\n[INFO] \n[INFO] --- maven-compiler-plugin:3.0:testCompile (default-testCompile) @ spring-data-book-jpa ---\n[INFO] Changes detected - recompiling the module!\n[INFO] Compiling 9 source files to /home/joe/dev/spring-data-book/jpa/target/test-classes\n[INFO] \n[INFO] --- maven-surefire-plugin:2.13:test (default-test) @ spring-data-book-jpa ---\n[INFO] Surefire report directory: /home/joe/dev/spring-data-book/jpa/target/surefire-reports\n\n---\n##  T E S T S\n\nRunning com.oreilly.springdata.jpa.core.ProductRepositoryIntegrationTest\n2016-03-25 15:03:12,928  INFO ontext.support.GenericApplicationContext: 510 - Refreshing org.springframework.context.support.GenericApplicationContext@56aac163: startup date [Fri Mar 25 15:03:12 MDT 2016]; root of context hierarchy\n2016-03-25 15:03:13,006 ERROR ramework.test.context.TestContextManager: 315 - Caught exception while allowing TestExecutionListener [org.springframework.test.context.support.DependencyInjectionTestExecutionListener@4fe767f3] to prepare test instance [com.oreilly.springdata.jpa.core.ProductRepositoryIntegrationTest@2805c96b]\njava.lang.IllegalStateException: Failed to load ApplicationContext\n    at org.springframework.test.context.TestContext.getApplicationContext(TestContext.java:157) ~[spring-test-3.2.1.RELEASE.jar:3.2.1.RELEASE]\n    at org.springframework.test.context.support.DependencyInjectionTestExecutionListener.injectDependencies(DependencyInjectionTestExecutionListener.java:109) ~[spring-test-3.2.1.RELEASE.jar:3.2.1.RELEASE]\n    at org.springframework.test.context.support.DependencyInjectionTestExecutionListener.prepareTestInstance(DependencyInjectionTestExecutionListener.java:75) ~[spring-test-3.2.1.RELEASE.jar:3.2.1.RELEASE]\n    at org.springframework.test.context.TestContextManager.prepareTestInstance(TestContextManager.java:313) ~[spring-test-3.2.1.RELEASE.jar:3.2.1.RELEASE]\n    at org.springframework.test.context.junit4.SpringJUnit4ClassRunner.createTest(SpringJUnit4ClassRunner.java:211) [spring-test-3.2.1.RELEASE.jar:3.2.1.RELEASE]\n    at org.springframework.test.context.junit4.SpringJUnit4ClassRunner$1.runReflectiveCall(SpringJUnit4ClassRunner.java:288) [spring-test-3.2.1.RELEASE.jar:3.2.1.RELEASE]\n    at org.junit.internal.runners.model.ReflectiveCallable.run(ReflectiveCallable.java:15) [junit-dep-4.10.jar:na]\n    at org.springframework.test.context.junit4.SpringJUnit4ClassRunner.methodBlock(SpringJUnit4ClassRunner.java:284) [spring-test-3.2.1.RELEASE.jar:3.2.1.RELEASE]\n    at org.springframework.test.context.junit4.SpringJUnit4ClassRunner.runChild(SpringJUnit4ClassRunner.java:231) [spring-test-3.2.1.RELEASE.jar:3.2.1.RELEASE]\n    at org.springframework.test.context.junit4.SpringJUnit4ClassRunner.runChild(SpringJUnit4ClassRunner.java:88) [spring-test-3.2.1.RELEASE.jar:3.2.1.RELEASE]\n    at org.junit.runners.ParentRunner$3.run(ParentRunner.java:231) [junit-dep-4.10.jar:na]\n    at org.junit.runners.ParentRunner$1.schedule(ParentRunner.java:60) [junit-dep-4.10.jar:na]\n    at org.junit.runners.ParentRunner.runChildren(ParentRunner.java:229) [junit-dep-4.10.jar:na]\n    at org.junit.runners.ParentRunner.access$000(ParentRunner.java:50) [junit-dep-4.10.jar:na]\n    at org.junit.runners.ParentRunner$2.evaluate(ParentRunner.java:222) [junit-dep-4.10.jar:na]\n    at org.springframework.test.context.junit4.statements.RunBeforeTestClassCallbacks.evaluate(RunBeforeTestClassCallbacks.java:61) [spring-test-3.2.1.RELEASE.jar:3.2.1.RELEASE]\n    at org.springframework.test.context.junit4.statements.RunAfterTestClassCallbacks.evaluate(RunAfterTestClassCallbacks.java:71) [spring-test-3.2.1.RELEASE.jar:3.2.1.RELEASE]\n    at org.junit.runners.ParentRunner.run(ParentRunner.java:300) [junit-dep-4.10.jar:na]\n    at org.springframework.test.context.junit4.SpringJUnit4ClassRunner.run(SpringJUnit4ClassRunner.java:174) [spring-test-3.2.1.RELEASE.jar:3.2.1.RELEASE]\n    at org.apache.maven.surefire.junit4.JUnit4Provider.execute(JUnit4Provider.java:264) [surefire-junit4-2.13.jar:2.13]\n    at org.apache.maven.surefire.junit4.JUnit4Provider.executeTestSet(JUnit4Provider.java:153) [surefire-junit4-2.13.jar:2.13]\n    at org.apache.maven.surefire.junit4.JUnit4Provider.invoke(JUnit4Provider.java:124) [surefire-junit4-2.13.jar:2.13]\n    at sun.reflect.NativeMethodAccessorImpl.invoke0(Native Method) ~[na:1.8.0_74]\n    at sun.reflect.NativeMethodAccessorImpl.invoke(NativeMethodAccessorImpl.java:62) ~[na:1.8.0_74]\n    at sun.reflect.DelegatingMethodAccessorImpl.invoke(DelegatingMethodAccessorImpl.java:43) ~[na:1.8.0_74]\n    at java.lang.reflect.Method.invoke(Method.java:498) ~[na:1.8.0_74]\n    at org.apache.maven.surefire.util.ReflectionUtils.invokeMethodWithArray2(ReflectionUtils.java:208) [surefire-api-2.13.jar:2.13]\n    at org.apache.maven.surefire.booter.ProviderFactory$ProviderProxy.invoke(ProviderFactory.java:158) [surefire-booter-2.13.jar:2.13]\n    at org.apache.maven.surefire.booter.ProviderFactory.invokeProvider(ProviderFactory.java:86) [surefire-booter-2.13.jar:2.13]\n    at org.apache.maven.surefire.booter.ForkedBooter.runSuitesInProcess(ForkedBooter.java:153) [surefire-booter-2.13.jar:2.13]\n    at org.apache.maven.surefire.booter.ForkedBooter.main(ForkedBooter.java:95) [surefire-booter-2.13.jar:2.13]\nCaused by: java.lang.IllegalArgumentException: null\n    at org.springframework.asm.ClassReader.<init>(Unknown Source) ~[spring-core-3.2.1.RELEASE.jar:3.2.1.RELEASE]\n    at org.springframework.asm.ClassReader.<init>(Unknown Source) ~[spring-core-3.2.1.RELEASE.jar:3.2.1.RELEASE]\n    at org.springframework.asm.ClassReader.<init>(Unknown Source) ~[spring-core-3.2.1.RELEASE.jar:3.2.1.RELEASE]\n<snip>\nResults :\n\nTests in error: \n   \u00bb IllegalState Failed to load ApplicationContext\n   \u00bb IllegalState Failed to load ApplicationContext\n   \u00bb IllegalState Failed to load ApplicationContext\n   \u00bb IllegalState Failed to load ApplicationContext\n   \u00bb IllegalState Failed to load ApplicationContext\n   \u00bb IllegalState Failed to load ApplicationContext\n   \u00bb IllegalState Failed to load ApplicationContext\n   \u00bb IllegalState Failed to load ApplicationContext\n   \u00bb IllegalState Failed to load ApplicationContext\n  ApplicationConfigTest.bootstrapAppFromJavaConfig:38 \u00bb IllegalArgument\n  ApplicationConfigTest.bootstrapAppFromXml:46 \u00bb BeanDefinitionParsing Configura...\n   \u00bb IllegalState Failed to load ApplicationContext\n   \u00bb IllegalState Failed to load ApplicationContext\n\nTests run: 13, Failures: 0, Errors: 13, Skipped: 0\n\n[INFO] ------------------------------------------------------------------------\n[INFO] Reactor Summary:\n[INFO] \n[INFO] Spring Data Book ................................... SUCCESS [  0.139 s]\n[INFO] Spring Data Book - JPA ............................. FAILURE [  3.349 s]\n[INFO] Spring Data Book - MongoDB ......................... SKIPPED\n[INFO] Spring Data Book - Querydsl ........................ SKIPPED\n[INFO] Spring Data Book - Neo4J ........................... SKIPPED\n[INFO] Spring Data Book - JDBC ............................ SKIPPED\n[INFO] Spring Data Book - Redis ........................... SKIPPED\n[INFO] Spring Data Book - GemFire ......................... SKIPPED\n[INFO] Spring Data Book - REST exporter ................... SKIPPED\n[INFO] ------------------------------------------------------------------------\n[INFO] BUILD FAILURE\n[INFO] ------------------------------------------------------------------------\n[INFO] Total time: 3.647 s\n[INFO] Finished at: 2016-03-25T15:03:13-06:00\n[INFO] Final Memory: 23M/283M\n[INFO] ------------------------------------------------------------------------\n[ERROR] Failed to execute goal org.apache.maven.plugins:maven-surefire-plugin:2.13:test (default-test) on project spring-data-book-jpa: There are test failures.\n[ERROR] \n[ERROR] Please refer to /home/joe/dev/spring-data-book/jpa/target/surefire-reports for the individual test results.\n[ERROR] -> [Help 1]\n[ERROR] \n[ERROR] To see the full stack trace of the errors, re-run Maven with the -e switch.\n[ERROR] Re-run Maven using the -X switch to enable full debug logging.\n[ERROR] \n[ERROR] For more information about the errors and possible solutions, please read the following articles:\n[ERROR] [Help 1] http://cwiki.apache.org/confluence/display/MAVEN/MojoFailureException\n[ERROR] \n[ERROR] After correcting the problems, you can resume the build with the command\n[ERROR]   mvn <goals> -rf :spring-data-book-jpa\n`\n\nI attached the full stack trace to this comment.\n", "reactions": {"url": "https://api.github.com/repos/spring-projects/spring-data-book/issues/21/reactions", "total_count": 0, "+1": 0, "-1": 0, "laugh": 0, "hooray": 0, "confused": 0, "heart": 0}, "author_association": "NONE"}], "commits": [], "pull_requests": [], "issue_comments": [], "commit_comments": [], "review_comments": []}, "ghost": {"issues": [{"url": "https://api.github.com/repos/spring-projects/spring-data-book/issues/18", "title": "whether waitForLock  api can be removed?", "body": "Hi All: \nI got a question like this:\n1. Why clear operation not use flushDB? Evict each key may be so slowly ? (@see xxx...RedisCache)\n2. Why GET/PUT and other operations need to wait for a lock.If I remove this lock what will happen?(@see xxx...RedisCache)\n", "reactions": {"url": "https://api.github.com/repos/spring-projects/spring-data-book/issues/18/reactions", "total_count": 0, "+1": 0, "-1": 0, "laugh": 0, "hooray": 0, "confused": 0, "heart": 0}, "author_association": "NONE"}], "commits": [], "pull_requests": [], "issue_comments": [{"url": "https://api.github.com/repos/spring-projects/spring-data-book/issues/comments/187515829", "body": "Hi author: \nI got a question like this:\n1. Why clear operation not use flushDB? evict each key may be so slowly ? (@see xxx...RedisCache)\n2. Why GET/PUT and other operations need to wait for a lock.If I remove this lock what will happen?(@see xxx...RedisCache)\nWaiting for ur response\nBest Regards from Eric\n", "reactions": {"url": "https://api.github.com/repos/spring-projects/spring-data-book/issues/comments/187515829/reactions", "total_count": 0, "+1": 0, "-1": 0, "laugh": 0, "hooray": 0, "confused": 0, "heart": 0}, "author_association": "NONE"}], "commit_comments": [], "review_comments": []}, "gautamdey": {"issues": [{"url": "https://api.github.com/repos/spring-projects/spring-data-book/issues/17", "title": "Compilation error in ApplicationConfig", "body": "the below code is from the book which does not compile on the line \ntxManager.setEntityManagerFactory(entityManagerFactory());\n\nHere is the error \n\n\"The method setEntityManagerFactory(EntityManagerFactory) in the type JpaTransactionManager is not applicable for the arguments (LocalContainerEntityManagerFactoryBean)\"\n\nBelow is the code copied from the book. \n\n/*\n- Copyright 2012 the original author or authors.\n  *\n- Licensed under the Apache License, Version 2.0 (the \"License\");\n- you may not use this file except in compliance with the License.\n- You may obtain a copy of the License at\n  *\n-      http://www.apache.org/licenses/LICENSE-2.0\n  *\n- Unless required by applicable law or agreed to in writing, software\n- distributed under the License is distributed on an \"AS IS\" BASIS,\n- WITHOUT WARRANTIES OR CONDITIONS OF ANY KIND, either express or implied.\n- See the License for the specific language governing permissions and\n- limitations under the License.\n  */\n  package com.oreilly.springdata.jpa;\n\nimport javax.sql.DataSource;\n\nimport org.springframework.context.annotation.Bean;\nimport org.springframework.context.annotation.Configuration;\nimport org.springframework.context.annotation.Import;\nimport org.springframework.data.jpa.repository.config.EnableJpaRepositories;\nimport org.springframework.jdbc.datasource.embedded.EmbeddedDatabase;\nimport org.springframework.jdbc.datasource.embedded.EmbeddedDatabaseBuilder;\nimport org.springframework.jdbc.datasource.embedded.EmbeddedDatabaseType;\nimport org.springframework.orm.jpa.JpaTransactionManager;\nimport org.springframework.orm.jpa.LocalContainerEntityManagerFactoryBean;\nimport org.springframework.orm.jpa.vendor.Database;\nimport org.springframework.orm.jpa.vendor.HibernateJpaVendorAdapter;\nimport org.springframework.transaction.PlatformTransactionManager;\nimport org.springframework.transaction.annotation.EnableTransactionManagement;\n\n/**\n- JavaConfig class to enable Spring Data JPA repositories. Re-using common infrastructure configuration from\n- {@link InfrastructureConfig}.\n- \n- @author Oliver Gierke\n  */\n  @Configuration\n  @EnableTransactionManagement\n  @EnableJpaRepositories\n  @Import(InfrastructureConfig.class)\n  public class ApplicationConfig {\n  @Bean \n  public DataSource dataSource(){\n      EmbeddedDatabaseBuilder builder = new EmbeddedDatabaseBuilder();\n      return builder.setType(EmbeddedDatabaseType.HSQL).build();\n  }\n  \n  @Bean \n  public LocalContainerEntityManagerFactoryBean entityManagerFactory(){\n      HibernateJpaVendorAdapter vendorAdapter = new HibernateJpaVendorAdapter();\n      vendorAdapter.setDatabase(Database.HSQL);\n      vendorAdapter.setGenerateDdl(true);\n  \n  ```\n  LocalContainerEntityManagerFactoryBean factory = new LocalContainerEntityManagerFactoryBean();\n  factory.setJpaVendorAdapter(vendorAdapter);\n  factory.setPackagesToScan(getClass().getPackage().getName());\n  factory.setDataSource(dataSource());\n  return factory ;\n  ```\n  \n  }\n  \n  @Bean \n  public PlatformTransactionManager transactionManager(){\n      JpaTransactionManager txManager = new JpaTransactionManager();\n      txManager.setEntityManagerFactory(entityManagerFactory());\n      return txManager;\n  }\n\n}\n", "reactions": {"url": "https://api.github.com/repos/spring-projects/spring-data-book/issues/17/reactions", "total_count": 0, "+1": 0, "-1": 0, "laugh": 0, "hooray": 0, "confused": 0, "heart": 0}, "author_association": "NONE"}], "commits": [], "pull_requests": [], "issue_comments": [{"url": "https://api.github.com/repos/spring-projects/spring-data-book/issues/comments/156911641", "body": "If I change the code to \n@Bean \n    public PlatformTransactionManager transactionManager(final EntityManagerFactory emf){\n        JpaTransactionManager txManager = new JpaTransactionManager();\n        txManager.setEntityManagerFactory(emf);\n        return txManager;\n    }\n\nit compiles but I get error when I try to run the CustomerRepositoryIntegrationTest\n\n2015-11-15 20:24:37,844  INFO ontext.support.GenericApplicationContext: 510 - Refreshing org.springframework.context.support.GenericApplicationContext@72d818d1: startup date [Sun Nov 15 20:24:37 PST 2015]; root of context hierarchy\n2015-11-15 20:24:37,893 ERROR ramework.test.context.TestContextManager: 315 - Caught exception while allowing TestExecutionListener [org.springframework.test.context.support.DependencyInjectionTestExecutionListener@29f69090] to prepare test instance [com.oreilly.springdata.jpa.core.CustomerRepositoryIntegrationTest@568bf312]\njava.lang.IllegalStateException: Failed to load ApplicationContext\n    at org.springframework.test.context.TestContext.getApplicationContext(TestContext.java:157) ~[spring-test-3.2.1.RELEASE.jar:3.2.1.RELEASE]\n    at org.springframework.test.context.support.DependencyInjectionTestExecutionListener.injectDependencies(DependencyInjectionTestExecutionListener.java:109) ~[spring-test-3.2.1.RELEASE.jar:3.2.1.RELEASE]\n    at org.springframework.test.context.support.DependencyInjectionTestExecutionListener.prepareTestInstance(DependencyInjectionTestExecutionListener.java:75) ~[spring-test-3.2.1.RELEASE.jar:3.2.1.RELEASE]\n    at org.springframework.test.context.TestContextManager.prepareTestInstance(TestContextManager.java:313) ~[spring-test-3.2.1.RELEASE.jar:3.2.1.RELEASE]\n    at org.springframework.test.context.junit4.SpringJUnit4ClassRunner.createTest(SpringJUnit4ClassRunner.java:211) [spring-test-3.2.1.RELEASE.jar:3.2.1.RELEASE]\n    at org.springframework.test.context.junit4.SpringJUnit4ClassRunner$1.runReflectiveCall(SpringJUnit4ClassRunner.java:288) [spring-test-3.2.1.RELEASE.jar:3.2.1.RELEASE]\n    at org.junit.internal.runners.model.ReflectiveCallable.run(ReflectiveCallable.java:15) [junit-dep-4.10.jar:na]\n    at org.springframework.test.context.junit4.SpringJUnit4ClassRunner.methodBlock(SpringJUnit4ClassRunner.java:284) [spring-test-3.2.1.RELEASE.jar:3.2.1.RELEASE]\n    at org.springframework.test.context.junit4.SpringJUnit4ClassRunner.runChild(SpringJUnit4ClassRunner.java:231) [spring-test-3.2.1.RELEASE.jar:3.2.1.RELEASE]\n    at org.springframework.test.context.junit4.SpringJUnit4ClassRunner.runChild(SpringJUnit4ClassRunner.java:88) [spring-test-3.2.1.RELEASE.jar:3.2.1.RELEASE]\n    at org.junit.runners.ParentRunner$3.run(ParentRunner.java:231) [junit-dep-4.10.jar:na]\n    at org.junit.runners.ParentRunner$1.schedule(ParentRunner.java:60) [junit-dep-4.10.jar:na]\n    at org.junit.runners.ParentRunner.runChildren(ParentRunner.java:229) [junit-dep-4.10.jar:na]\n    at org.junit.runners.ParentRunner.access$000(ParentRunner.java:50) [junit-dep-4.10.jar:na]\n    at org.junit.runners.ParentRunner$2.evaluate(ParentRunner.java:222) [junit-dep-4.10.jar:na]\n    at org.springframework.test.context.junit4.statements.RunBeforeTestClassCallbacks.evaluate(RunBeforeTestClassCallbacks.java:61) [spring-test-3.2.1.RELEASE.jar:3.2.1.RELEASE]\n    at org.springframework.test.context.junit4.statements.RunAfterTestClassCallbacks.evaluate(RunAfterTestClassCallbacks.java:71) [spring-test-3.2.1.RELEASE.jar:3.2.1.RELEASE]\n    at org.junit.runners.ParentRunner.run(ParentRunner.java:300) [junit-dep-4.10.jar:na]\n    at org.springframework.test.context.junit4.SpringJUnit4ClassRunner.run(SpringJUnit4ClassRunner.java:174) [spring-test-3.2.1.RELEASE.jar:3.2.1.RELEASE]\n    at org.eclipse.jdt.internal.junit4.runner.JUnit4TestReference.run(JUnit4TestReference.java:86) [.cp/:na]\n    at org.eclipse.jdt.internal.junit.runner.TestExecution.run(TestExecution.java:38) [.cp/:na]\n    at org.eclipse.jdt.internal.junit.runner.RemoteTestRunner.runTests(RemoteTestRunner.java:459) [.cp/:na]\n    at org.eclipse.jdt.internal.junit.runner.RemoteTestRunner.runTests(RemoteTestRunner.java:675) [.cp/:na]\n    at org.eclipse.jdt.internal.junit.runner.RemoteTestRunner.run(RemoteTestRunner.java:382) [.cp/:na]\n    at org.eclipse.jdt.internal.junit.runner.RemoteTestRunner.main(RemoteTestRunner.java:192) [.cp/:na]\nCaused by: java.lang.IllegalArgumentException: null\n    at org.springframework.asm.ClassReader.<init>(Unknown Source) ~[spring-core-3.2.1.RELEASE.jar:3.2.1.RELEASE]\n    at org.springframework.asm.ClassReader.<init>(Unknown Source) ~[spring-core-3.2.1.RELEASE.jar:3.2.1.RELEASE]\n    at org.springframework.asm.ClassReader.<init>(Unknown Source) ~[spring-core-3.2.1.RELEASE.jar:3.2.1.RELEASE]\n    at org.springframework.core.type.classreading.SimpleMetadataReader.<init>(SimpleMetadataReader.java:52) ~[spring-core-3.2.1.RELEASE.jar:3.2.1.RELEASE]\n    at org.springframework.core.type.classreading.SimpleMetadataReaderFactory.getMetadataReader(SimpleMetadataReaderFactory.java:80) ~[spring-core-3.2.1.RELEASE.jar:3.2.1.RELEASE]\n    at org.springframework.core.type.classreading.CachingMetadataReaderFactory.getMetadataReader(CachingMetadataReaderFactory.java:102) ~[spring-core-3.2.1.RELEASE.jar:3.2.1.RELEASE]\n    at org.springframework.core.type.classreading.SimpleMetadataReaderFactory.getMetadataReader(SimpleMetadataReaderFactory.java:76) ~[spring-core-3.2.1.RELEASE.jar:3.2.1.RELEASE]\n    at org.springframework.context.annotation.ConfigurationClassParser.getImports(ConfigurationClassParser.java:298) ~[spring-context-3.2.1.RELEASE.jar:3.2.1.RELEASE]\n    at org.springframework.context.annotation.ConfigurationClassParser.getImports(ConfigurationClassParser.java:300) ~[spring-context-3.2.1.RELEASE.jar:3.2.1.RELEASE]\n    at org.springframework.context.annotation.ConfigurationClassParser.getImports(ConfigurationClassParser.java:300) ~[spring-context-3.2.1.RELEASE.jar:3.2.1.RELEASE]\n    at org.springframework.context.annotation.ConfigurationClassParser.doProcessConfigurationClass(ConfigurationClassParser.java:230) ~[spring-context-3.2.1.RELEASE.jar:3.2.1.RELEASE]\n    at org.springframework.context.annotation.ConfigurationClassParser.processConfigurationClass(ConfigurationClassParser.java:153) ~[spring-context-3.2.1.RELEASE.jar:3.2.1.RELEASE]\n    at org.springframework.context.annotation.ConfigurationClassParser.parse(ConfigurationClassParser.java:139) ~[spring-context-3.2.1.RELEASE.jar:3.2.1.RELEASE]\n    at org.springframework.context.annotation.ConfigurationClassPostProcessor.processConfigBeanDefinitions(ConfigurationClassPostProcessor.java:282) ~[spring-context-3.2.1.RELEASE.jar:3.2.1.RELEASE]\n    at org.springframework.context.annotation.ConfigurationClassPostProcessor.postProcessBeanDefinitionRegistry(ConfigurationClassPostProcessor.java:223) ~[spring-context-3.2.1.RELEASE.jar:3.2.1.RELEASE]\n    at org.springframework.context.support.AbstractApplicationContext.invokeBeanFactoryPostProcessors(AbstractApplicationContext.java:630) ~[spring-context-3.2.1.RELEASE.jar:3.2.1.RELEASE]\n    at org.springframework.context.support.AbstractApplicationContext.refresh(AbstractApplicationContext.java:461) ~[spring-context-3.2.1.RELEASE.jar:3.2.1.RELEASE]\n    at org.springframework.test.context.support.AbstractGenericContextLoader.loadContext(AbstractGenericContextLoader.java:106) ~[spring-test-3.2.1.RELEASE.jar:3.2.1.RELEASE]\n    at org.springframework.test.context.support.AbstractGenericContextLoader.loadContext(AbstractGenericContextLoader.java:57) ~[spring-test-3.2.1.RELEASE.jar:3.2.1.RELEASE]\n    at org.springframework.test.context.support.AbstractDelegatingSmartContextLoader.delegateLoading(AbstractDelegatingSmartContextLoader.java:100) ~[spring-test-3.2.1.RELEASE.jar:3.2.1.RELEASE]\n    at org.springframework.test.context.support.AbstractDelegatingSmartContextLoader.loadContext(AbstractDelegatingSmartContextLoader.java:248) ~[spring-test-3.2.1.RELEASE.jar:3.2.1.RELEASE]\n    at org.springframework.test.context.TestContext.loadApplicationContext(TestContext.java:124) ~[spring-test-3.2.1.RELEASE.jar:3.2.1.RELEASE]\n    at org.springframework.test.context.TestContext.getApplicationContext(TestContext.java:148) ~[spring-test-3.2.1.RELEASE.jar:3.2.1.RELEASE]\n    ... 24 common frames omitted\n", "reactions": {"url": "https://api.github.com/repos/spring-projects/spring-data-book/issues/comments/156911641/reactions", "total_count": 0, "+1": 0, "-1": 0, "laugh": 0, "hooray": 0, "confused": 0, "heart": 0}, "author_association": "NONE"}], "commit_comments": [], "review_comments": []}, "moke110007": {"issues": [{"url": "https://api.github.com/repos/spring-projects/spring-data-book/issues/15", "title": "QCustomer and QProduct  Can't be found in projects.", "body": "1. QCustomer cannot be resolved to a type  \n2. QProduct cannot be resolved to a type\n", "reactions": {"url": "https://api.github.com/repos/spring-projects/spring-data-book/issues/15/reactions", "total_count": 0, "+1": 0, "-1": 0, "laugh": 0, "hooray": 0, "confused": 0, "heart": 0}, "author_association": "NONE"}], "commits": [], "pull_requests": [], "issue_comments": [], "commit_comments": [], "review_comments": []}, "wxlund": {"issues": [{"url": "https://api.github.com/repos/spring-projects/spring-data-book/issues/11", "title": "Unit tests using redisTemplate fail", "body": "KeyValueSerializersTest and CachingTest fail with:\n\njava.lang.IllegalArgumentException: template not initialized; call afterPropertiesSet() before using it\n    at org.springframework.util.Assert.isTrue(Assert.java:65)\n    at org.springframework.data.redis.core.RedisTemplate.execute(RedisTemplate.java:151)\n    at org.springframework.data.redis.core.RedisTemplate.execute(RedisTemplate.java:137)\n    at org.springframework.data.redis.core.AbstractOperations.execute(AbstractOperations.java:84)\n    at org.springframework.data.redis.core.DefaultValueOperations.setIfAbsent(DefaultValueOperations.java:204)\n    at com.oreilly.springdata.redis.KeyValueSerializersTest.testStringLongSerializers(KeyValueSerializersTest.java:34)\n\nWhat needs to be done to initialize the redisTemplate?\n", "reactions": {"url": "https://api.github.com/repos/spring-projects/spring-data-book/issues/11/reactions", "total_count": 0, "+1": 0, "-1": 0, "laugh": 0, "hooray": 0, "confused": 0, "heart": 0}, "author_association": "NONE"}, {"url": "https://api.github.com/repos/spring-projects/spring-data-book/issues/10", "title": "spring-data-redis ApplicationConfigTest fails", "body": " Instantiation of bean failed; nested exception is org.springframework.beans.BeanInstantiationException: Could not instantiate bean class [com.oreilly.springdata.redis.ApplicationConfig]: Is it an abstract class?; nested exception is java.lang.InstantiationException.\n\nWhen I remove abstract from public class ApplicationConfigTest {} the test works.  Was this an oversite or did I miss something?\n", "reactions": {"url": "https://api.github.com/repos/spring-projects/spring-data-book/issues/10/reactions", "total_count": 0, "+1": 0, "-1": 0, "laugh": 0, "hooray": 0, "confused": 0, "heart": 0}, "author_association": "NONE"}], "commits": [], "pull_requests": [], "issue_comments": [], "commit_comments": [], "review_comments": []}, "blwin2010": {"issues": [{"url": "https://api.github.com/repos/spring-projects/spring-data-book/issues/9", "title": "how to @Autowired a interface Customer", "body": "I see your example,but i set up a service layer and use \"@Autowired\" to Ioc the CustomerRepository.It doesn't success.\"there is no bean defined that type is CustomerRepository\".Help! \n", "reactions": {"url": "https://api.github.com/repos/spring-projects/spring-data-book/issues/9/reactions", "total_count": 0, "+1": 0, "-1": 0, "laugh": 0, "hooray": 0, "confused": 0, "heart": 0}, "author_association": "NONE"}], "commits": [], "pull_requests": [], "issue_comments": [], "commit_comments": [], "review_comments": []}, "olivergierke": {"issues": [{"url": "https://api.github.com/repos/spring-projects/spring-data-book/issues/7", "title": "Upgrade to latest dependency versions", "body": "", "reactions": {"url": "https://api.github.com/repos/spring-projects/spring-data-book/issues/7/reactions", "total_count": 0, "+1": 0, "-1": 0, "laugh": 0, "hooray": 0, "confused": 0, "heart": 0}, "author_association": "OWNER"}], "commits": [{"url": "https://api.github.com/repos/spring-projects/spring-data-book/commits/7889f38547bf99c1cb645eb074f0a320a9d4b845", "message": "#3 - Upgraded to Mysema APT plugin in 1.0.8."}, {"url": "https://api.github.com/repos/spring-projects/spring-data-book/commits/9e96426175f3a05819894b4478943da2a3cb7799", "message": "Set UTF-8 as build encoding."}, {"url": "https://api.github.com/repos/spring-projects/spring-data-book/commits/b9b79e8f841b5b107743f07d17b3ec234c473a52", "message": "Upgraded to Spring Data REST 1.1.0.M1.\n\nAdapted configuration setup where necessary. Upgraded to Jetty 9 RC2 to be able to use Spring base class for WebApplicationInitializers. Upgraded sources to Jackson 2."}, {"url": "https://api.github.com/repos/spring-projects/spring-data-book/commits/9d6630bca44b4e3c3d7ccf355bd323bd61905991", "message": "Upgraded to Spring Data Arora release train.\n\nUpgraded to Spring Data JPA 1.3.0.RELEASE, Spring Data MongoDB 1.2.0.RELEASE, Spring Data Neo4j 2.2.0.RELEASE, Spring Data Gemfire 1.3.0.M1, Spring Data Redis 1.0.3.RELEASE."}, {"url": "https://api.github.com/repos/spring-projects/spring-data-book/commits/e2414d1b08c09a5caa39f70ca7547760e8efbf78", "message": "Dependency updates.\n\nUpdated to Spring 3.2.1.RELEASE plus necessary additional dependency declarations. Moved repository declaration to Gemfire as it's only needed to pull in the Gemfire JAR. Upgraded to Hibernate 4.1.9, HSQLDB 2.2.9, QueryDsl 2.9.0. Upgraded plugin dependencies to compiler plugin 3.0, Surefire plugin 2.13."}, {"url": "https://api.github.com/repos/spring-projects/spring-data-book/commits/984cf8297c2e897bed21824d6ba158dafcac1f60", "message": "Upgraded to Spring 3.2.0.RC1."}, {"url": "https://api.github.com/repos/spring-projects/spring-data-book/commits/7124dd01ba670aef6a2d499538d6a80dd9fd3d36", "message": "Upgraded to Querydsl 2.8.2."}, {"url": "https://api.github.com/repos/spring-projects/spring-data-book/commits/a1181efbcdb8b9e78437bc57d9370d24d7d783f8", "message": "Dependency updates - Upgraded to latest Spring Data releases.\n\nSpring Data Gemfire - 1.2.1.RELEASE\nSpring Data JPA - 1.2.0.RELEASE\nSpring Data MongoDB - 1.1.1.RELEASE\nSpring Data Neo4j - 2.1.0.RELEASE\nSpring Data REST - 1.0.0.RELEASE\n\nPolished Querydsl configuration to be consistent across modules."}, {"url": "https://api.github.com/repos/spring-projects/spring-data-book/commits/68b634bf541aa9f71c29f0347afd1abdd3131e59", "message": "JDBC - Updated generated query classes."}, {"url": "https://api.github.com/repos/spring-projects/spring-data-book/commits/0412efa1ee93da3f6e13aa8fbaa82227dbffe3b0", "message": "Dependencies - Updated to latest Spring Data module releases."}, {"url": "https://api.github.com/repos/spring-projects/spring-data-book/commits/6f3d5844774be26fe621f96d8211f8995c2a92b1", "message": "#2 - Restructured JavaConfig configuration classes to improve understandability.\n\nSplit up configuration classes into ApplicationConfig (enabling Spring Data JPA repositories), PlainJpaConfig (enabling component scanning to pick up the manual implementation) both sharing common infrastructure setup in InfrastructureConfig (setting up a DataSource, EntityManagerFactory and PlatformTRansactionManager).\n\nThis removes the need to use profiles and allows a clean separation of Spring Data JPA setup from the manual implementation one."}, {"url": "https://api.github.com/repos/spring-projects/spring-data-book/commits/3358bbbe9fac95cb914af4fded803d026a340ff3", "message": "REST - Clean up logging configuration."}, {"url": "https://api.github.com/repos/spring-projects/spring-data-book/commits/7bea02ecbaceb0e54a6d553f1ce9be2282e20e00", "message": "REST - Improved logging in SampleDataProvider."}, {"url": "https://api.github.com/repos/spring-projects/spring-data-book/commits/1e790482dd7ec981848d53d20177e08a3215fedc", "message": "Upgraded Jetty plugin to 8.1.7."}, {"url": "https://api.github.com/repos/spring-projects/spring-data-book/commits/5c975dc3af50caaefce5fe1db410544e3346fa5e", "message": "Updagrede to SLF4j 1.7.1."}, {"url": "https://api.github.com/repos/spring-projects/spring-data-book/commits/364f659704cbad6da4ac59f22d14ad9e0096f33d", "message": "Removed explicit dependency to Spring Hateoas in 0.2.0.BUILD-SNAPSHOT.\n\nWe're currently using the version transitively pull ind through Spring Data REST."}, {"url": "https://api.github.com/repos/spring-projects/spring-data-book/commits/d897de452ad76a620eb682161999bfc13d16f956", "message": "Polished isValid(\u2026) method of EmailAddress value object."}, {"url": "https://api.github.com/repos/spring-projects/spring-data-book/commits/488f5c9960037bdb1d90dfd6ab9b02d163e465ec", "message": "Improved Querydsl setup."}, {"url": "https://api.github.com/repos/spring-projects/spring-data-book/commits/6915371952bfabe37ac7ffb19445c11295b923fd", "message": "Gemfire - Formatting."}, {"url": "https://api.github.com/repos/spring-projects/spring-data-book/commits/c713150bfed2a2a4a3b3da3e1a2823a11ee71cba", "message": "Querydsl - Removed obsolete classes."}, {"url": "https://api.github.com/repos/spring-projects/spring-data-book/commits/e2c2e75d160eb56d9e386ced023ed65546ebb962", "message": "Upgraded to Spring 3.2.0.M2."}, {"url": "https://api.github.com/repos/spring-projects/spring-data-book/commits/cc3c2cfe09d59438c217551f0a1e30f041cb78cc", "message": "Gemfire - Removed obsolete file."}, {"url": "https://api.github.com/repos/spring-projects/spring-data-book/commits/0e5aef0c5570dad83501f3e1b98c48e48072938d", "message": "REST - Improve application configuration."}, {"url": "https://api.github.com/repos/spring-projects/spring-data-book/commits/3b646dbcd6af7fa718068c297847ecee1580c0c5", "message": "Logging - Include Logback as runtime dependency."}, {"url": "https://api.github.com/repos/spring-projects/spring-data-book/commits/9c136c7b81f47b82b5db7f3cbf5b68011f163d55", "message": "JPA - Improve application configuration."}, {"url": "https://api.github.com/repos/spring-projects/spring-data-book/commits/fa0cfdb866cf1eb98e625679fa4866d6a27c7551", "message": "Build - General dependency updates.\n\nQuerydsl - 2.6.0 -> 2.7.2\nHamcrest - 1.2.1 -> 1.3\nSlf4j - 1.6.4 -> 1.6.6\nHibernate - 4.1.3.Final -> 4.1.6.Final\nSpring Data JPA - 1.2.0.M1 -> 1.2.0.BUILD-SNAPSHOT\nSpring Data Neo4J - 2.1.0.RC1 -> 2.1.0.BUILD-SNAPSHOT\nMaven Compiler Plugin - 2.4 -> 2.5.1\nMaven Surefire Plugin - 2.12 -> 2.12.2\n\nReplaced explicit Hamcrest versions with property."}, {"url": "https://api.github.com/repos/spring-projects/spring-data-book/commits/b934db8b6641c4d78f7e88dd9dfd276f8bd7beb3", "message": "JPA - Fixed Querydsl setup."}, {"url": "https://api.github.com/repos/spring-projects/spring-data-book/commits/9a208bde5cb9b8f3b9e73020fd720848525baa77", "message": "Build - Remove duplicate Gemfire module declaration."}, {"url": "https://api.github.com/repos/spring-projects/spring-data-book/commits/dcb7a92eaacf4ddb2de437ed20a1eefe480e3299", "message": "REST - Added sample clients accessing the exported repositories."}, {"url": "https://api.github.com/repos/spring-projects/spring-data-book/commits/e5c84ff0d98b982cb9b76bcc3d6ebbf039f54512", "message": "REST - Added Spring HATEOAS as dependency."}, {"url": "https://api.github.com/repos/spring-projects/spring-data-book/commits/1e2034125eeacb18d9a33ffbd820f371672c8b56", "message": "MongoDB - Added integration test for Querydsl usage."}, {"url": "https://api.github.com/repos/spring-projects/spring-data-book/commits/48bc445c3268e327f127e5b7994f0987ab1fdb02", "message": "Gemfire - Aligned project structure with the one of other modules.\n\nUnified customer, product and core package. Renamed CustomerDao to GemfireCustomerRepository. Updated application JavaConfig and test configuration."}, {"url": "https://api.github.com/repos/spring-projects/spring-data-book/commits/67c90acf33cecfa6105a969c9ab29693f6627ae9", "message": "MongoDB - Added Querydsl sample."}, {"url": "https://api.github.com/repos/spring-projects/spring-data-book/commits/22bed729fe42c427bc35aabacde50a26a8befad2", "message": "JPA - Added Querydsl sample."}, {"url": "https://api.github.com/repos/spring-projects/spring-data-book/commits/2c775b082b6b98bbc4dd085c99ded2144eaa0a2d", "message": "Mongo - Manual CustomerRepository implementation to show MongoTemplate usage."}, {"url": "https://api.github.com/repos/spring-projects/spring-data-book/commits/1b8b163d1bd662e2aceab388b0adb983b2dc4d41", "message": "Mongo - Using WriteConcern.SAFE to trigger DuplicateKeyException."}, {"url": "https://api.github.com/repos/spring-projects/spring-data-book/commits/285ab4aecb0a7a747dda5fb2bb7f8b2d22f7755a", "message": "REST - Configure logging."}, {"url": "https://api.github.com/repos/spring-projects/spring-data-book/commits/cbb1e149993a7253ea73848d2ddce354a7d3e0fd", "message": "JPA, Mongo - Added additional constructor to Order."}, {"url": "https://api.github.com/repos/spring-projects/spring-data-book/commits/0a2284ea3293ba74981be6682a2fce8397e0e1cd", "message": "Gemfire - Added Gemfire to modules.\n\nFormatted pom.xml."}, {"url": "https://api.github.com/repos/spring-projects/spring-data-book/commits/001c678fd31b0b13e5f2c9d321c4d98c20f4b0bd", "message": "REST - Minor tweaks to sample code.\n\nRemoved returning attributes as immutable map. Added constructors taking a billing address to Order. Let CustomerRepository extend PagingAndSortingRepository to be able to explain collection pagination. Added @Param annotations to repository methods to be able to execute the methods via exposed resources."}, {"url": "https://api.github.com/repos/spring-projects/spring-data-book/commits/f14997317b80a4a3ee7d1e5612814ab473d6afdc", "message": "REST - Removed obsolete dependency exclusion."}, {"url": "https://api.github.com/repos/spring-projects/spring-data-book/commits/aca5f6dbc1c73896e7ca577690ffddc65abd5834", "message": "Polishing."}, {"url": "https://api.github.com/repos/spring-projects/spring-data-book/commits/1646d69baa94a74650c34d453cc51e585ddb6b13", "message": "REST - Cleanups.\n\nPolished JavaDoc of SampleDataProvider. Cleaned up XML files."}, {"url": "https://api.github.com/repos/spring-projects/spring-data-book/commits/2b8f41225a3ee30b1dffbc88e9bd22bffbf738ff", "message": "Updated .gitignore."}, {"url": "https://api.github.com/repos/spring-projects/spring-data-book/commits/bf479b63dfe4a5b866145b9b28838a0a6f9d10e5", "message": "REST - Added annotations to customize JSON output."}, {"url": "https://api.github.com/repos/spring-projects/spring-data-book/commits/0587f2fe258969745566008276e595f04d4f510a", "message": "MongoDB - Move to snapshot build to benefit from entity scanning defaults."}, {"url": "https://api.github.com/repos/spring-projects/spring-data-book/commits/098356099c94b31a7ea2a4bd0acd9a6dd10d59a5", "message": "Infrastructure - Removed Gradle build."}, {"url": "https://api.github.com/repos/spring-projects/spring-data-book/commits/498a30eb11dac8d88e931ad552e24d2d8e74c449", "message": "REST - Renamed {rest-exporter => rest}."}, {"url": "https://api.github.com/repos/spring-projects/spring-data-book/commits/f37e721a61669e87642f6ffc14b13d1940949ac4", "message": "Maven, REST - Use snapshot repository for now."}, {"url": "https://api.github.com/repos/spring-projects/spring-data-book/commits/be4766804bff9e002c9c6506e93506517c2bf170", "message": "Added REST exporter module."}, {"url": "https://api.github.com/repos/spring-projects/spring-data-book/commits/222ccbac9aa85ab1ffa5dc71e58edf5474216acb", "message": "Cleaned up Gradle build.\n\nConsolidated dependency versions into build.gradle to avoid the indirection and the additional gradle.properties flying around. Added Logback dependency to root project and moved CGLib dependency into it as well. Removed obsolete dependency declarations mostly for Log4J."}, {"url": "https://api.github.com/repos/spring-projects/spring-data-book/commits/8fcf6f0f16594308e6b93e5c01cabd92d63053a9", "message": "Merge branch 'master' of https://github.com/SpringSource/spring-data-book\n\n* 'master' of https://github.com/SpringSource/spring-data-book:\n  Removing oracle example\n  Working on examples for Oracle"}, {"url": "https://api.github.com/repos/spring-projects/spring-data-book/commits/ad7a24dc2b41c41709e187c7a302c12229e3c963", "message": "Added formatter for Eclipse."}, {"url": "https://api.github.com/repos/spring-projects/spring-data-book/commits/16ac823343b46921924df1519ab65741f4dcdbb5", "message": "JDBC - Fixed code generation setup.\n\nQuerydsl now again generates into src/generated/java. Adapted both Maven and Gradle build accordingly."}, {"url": "https://api.github.com/repos/spring-projects/spring-data-book/commits/1b08ad9792fc37545df83a3973bc3c9b7aa782e2", "message": "Created pom.xml files to allow projects to be built using Maven."}, {"url": "https://api.github.com/repos/spring-projects/spring-data-book/commits/9a2ba3918d5d2d878dedc8e1dfe31778061282ab", "message": "JPA - Polished configuration and test case."}, {"url": "https://api.github.com/repos/spring-projects/spring-data-book/commits/e97e9298ebc85346cc1a5d56a15da50ce48ff97c", "message": "JPA - Update to Spring Data Commons 1.2.0.BUILD-SNAPSHOT."}, {"url": "https://api.github.com/repos/spring-projects/spring-data-book/commits/14865d0c4a7ca10b70d8c349a276818bc727345b", "message": "Merge branch 'master' of https://github.com/SpringSource/spring-data-book\n\n* 'master' of https://github.com/SpringSource/spring-data-book:\n  More example code for Redis chapter covering PubSub and Caching."}, {"url": "https://api.github.com/repos/spring-projects/spring-data-book/commits/9ceebc66a9a7da72d36f404539f1fd6e460871e6", "message": "Merge branch 'master' of https://github.com/SpringSource/spring-data-book\n\n* 'master' of https://github.com/SpringSource/spring-data-book:\n  cleanup SQL\n  Working on examples for Oracle\n  Working on examples for Oracle\n  Adding equals and hashCode to EmailAddress\n  Working on examples for JDBC/Querydsl/Oracle\n  Working on examples for JDBC/Querydsl\n  Refactoring QueryDSL JDBC example and tests"}, {"url": "https://api.github.com/repos/spring-projects/spring-data-book/commits/b7db2ebc92d06fc4120ad234d60ed6351bebd4ad", "message": "Neo4j - Fix generics in method declaration in repository."}, {"url": "https://api.github.com/repos/spring-projects/spring-data-book/commits/0f952f1366daa642b16b93742fc40fdc1b47f6cf", "message": "MongoDB / JPA - Cleanups."}, {"url": "https://api.github.com/repos/spring-projects/spring-data-book/commits/2568f995574cf7d8791e51098d66661ecacc6bf6", "message": "JPA - Adapted to improvement in defaulting of base package for annotation driven repository config."}, {"url": "https://api.github.com/repos/spring-projects/spring-data-book/commits/c9fe5824068ba3a6aa78e7fc0cc36e310cf29c2b", "message": "MongoDB - Upgrade to JavaConfig for repositories."}, {"url": "https://api.github.com/repos/spring-projects/spring-data-book/commits/c2e1863fad2c5c90f4ee0dae2d419e4d290ca291", "message": "Build - Maked 'build' default task for all modules."}, {"url": "https://api.github.com/repos/spring-projects/spring-data-book/commits/22eeb6903895d3b721b9d75bb9f1365c1ba412b4", "message": "JPA - Upgrade to JavaConfig.\n\nPull in snapshot version of JavaConfig coming up in Spring Data JPA. Simplified XML configuration."}, {"url": "https://api.github.com/repos/spring-projects/spring-data-book/commits/453dad41c19cc73aa4c120bb77f3b2f1aae0363d", "message": "MongoDB - Polished sample code and removed obsolete classes."}, {"url": "https://api.github.com/repos/spring-projects/spring-data-book/commits/58e9abdec87baed8036ca1378ea460128b8762b7", "message": "JPA - Polished LineItem mapping."}, {"url": "https://api.github.com/repos/spring-projects/spring-data-book/commits/a8686a71da450a5f18e6ab2f3ba8a19659097416", "message": "JPA - Polished sample code.\n\nAdded Javadoc, improved mapping of entities."}, {"url": "https://api.github.com/repos/spring-projects/spring-data-book/commits/a197aab5ec0d90b4507da2b602da6aaa8e4c9e3b", "message": "Upgrade Gradle build to Spring Data Commons 1.3.1.RELEASE."}, {"url": "https://api.github.com/repos/spring-projects/spring-data-book/commits/8eb1f684be3f1d33b78182c994de9141f692c9ac", "message": "Added MongoDB module.\n\nFixed Neo4J Integration tests. Let Querydsl module work with Maven as I failed to set up a proper APT processor with Gradle."}, {"url": "https://api.github.com/repos/spring-projects/spring-data-book/commits/c223a4dadf219d4e9836995220b37815c1dbedda", "message": "Upgraded Gradle wrapper to 1.0."}, {"url": "https://api.github.com/repos/spring-projects/spring-data-book/commits/1f0e9213c34ad18afecd41714fac2cdcd8dadc4d", "message": "Added submodule for Querydsl.\n\nShow working with Querydsl predicates using the plain collection query functionality. Added bin folder to the Git ignored folders. Build currently only working with Maven."}, {"url": "https://api.github.com/repos/spring-projects/spring-data-book/commits/069355d642cfcc7254d53e58dc31772e75287995", "message": "Build infrastructure.\n\nFixing Spring versions to 3.1.1 using { forced = true }. The same for Spring Data Commons 1.3.0.RELEASE. Upgraded to Hibernate 4.1.3.Final for JPA module. Removed jdbc module from settings.gradle as it cannot be built without artifacts added to the repo manually and thus breaks the build of the entire project."}, {"url": "https://api.github.com/repos/spring-projects/spring-data-book/commits/dba7316669af56787182b7dd18ab14bd98cf6a66", "message": "Updates to build infrastructure.\n\nExcluded junit:junit dependency to be sure Hamcrest library is used and not the subset of types shipped with JUnit. Switched to SpringSource milestone repository and include Maven Central. Removed superfluous dependency to Spring Context Support. Added global compile time dependency to Spring Data Commons. Move Logback config to redis module for now as we're using Log4j in the other modules currently. Moved version declarations of Spring Data JPA and Hibernate into JPA module. Reduced scopes for JPA module dependencies to the least necessary ones."}, {"url": "https://api.github.com/repos/spring-projects/spring-data-book/commits/bbfee6883e72a563a38b231b0a25817080dd7d58", "message": "JPA - Initial commit for JPA chapter sample code.\n\nUse the pom.xml file for building for now as I couldn't get dependencies resolved correctly for Gradle. Removed log back configuration as the module will use Log4J as logging library.\n\nAdded basic mapped domain model as well as infrastructure configuration in JavaConfig and XML. Added basic integration tests to test the mapping. Removed obsolete package-info.java files."}], "pull_requests": [], "issue_comments": [{"url": "https://api.github.com/repos/spring-projects/spring-data-book/issues/comments/8932096", "body": "Thanks for the pointer. The issue should have become obsolete with https://github.com/SpringSource/spring-data-book/commit/364f659704cbad6da4ac59f22d14ad9e0096f33d.\n", "reactions": {"url": "https://api.github.com/repos/spring-projects/spring-data-book/issues/comments/8932096/reactions", "total_count": 0, "+1": 0, "-1": 0, "laugh": 0, "hooray": 0, "confused": 0, "heart": 0}, "author_association": "OWNER"}, {"url": "https://api.github.com/repos/spring-projects/spring-data-book/issues/comments/14614925", "body": "Sorry for not getting to this earlier. I didn't really consider this as broken as we relied on 1.0.4 which _is_ available in Maven Central. I went ahead and upgraded the dependency to the new artifact in 1.0.8 in all modules using Querydsl. Thanks for spotting this though.\n", "reactions": {"url": "https://api.github.com/repos/spring-projects/spring-data-book/issues/comments/14614925/reactions", "total_count": 0, "+1": 0, "-1": 0, "laugh": 0, "hooray": 0, "confused": 0, "heart": 0}, "author_association": "OWNER"}, {"url": "https://api.github.com/repos/spring-projects/spring-data-book/issues/comments/14614984", "body": "/cc @dturanski\n", "reactions": {"url": "https://api.github.com/repos/spring-projects/spring-data-book/issues/comments/14614984/reactions", "total_count": 0, "+1": 0, "-1": 0, "laugh": 0, "hooray": 0, "confused": 0, "heart": 0}, "author_association": "OWNER"}, {"url": "https://api.github.com/repos/spring-projects/spring-data-book/issues/comments/22167514", "body": "Related: #5 \n", "reactions": {"url": "https://api.github.com/repos/spring-projects/spring-data-book/issues/comments/22167514/reactions", "total_count": 0, "+1": 0, "-1": 0, "laugh": 0, "hooray": 0, "confused": 0, "heart": 0}, "author_association": "OWNER"}], "commit_comments": [], "review_comments": []}, "thysmichels": {"issues": [{"url": "https://api.github.com/repos/spring-projects/spring-data-book/issues/6", "title": "REST: LifecycleExecutionException", "body": "> mvn clean package\n\n[INFO] Spring Data Book .................................. SUCCESS [0.232s]\n[INFO] Spring Data Book - JPA ............................ SUCCESS [8.206s]\n[INFO] Spring Data Book - MongoDB ........................ SUCCESS [4.052s]\n[INFO] Spring Data Book - Querydsl ....................... SUCCESS [1.701s]\n[INFO] Spring Data Book - Neo4J .......................... SUCCESS [8.326s]\n[INFO] Spring Data Book - JDBC ........................... SUCCESS [3.397s]\n[INFO] Spring Data Book - Redis .......................... SUCCESS [0.400s]\n[INFO] Spring Data Book - GemFire ........................ SUCCESS [35.907s]\n[INFO] Spring Data Book - REST exporter .................. FAILURE [0.549s]\n\norg.apache.maven.lifecycle.LifecycleExecutionException: Failed to execute goal org.apache.maven.plugins:maven-compiler-plugin:3.0:testCompile (default-testCompile) on project spring-data-book-rest: Compilation failure\nAn unknown compilation problem occurred\n\n```\nat org.apache.maven.lifecycle.internal.MojoExecutor.execute(MojoExecutor.java:213)\nat org.apache.maven.lifecycle.internal.MojoExecutor.execute(MojoExecutor.java:153)\nat org.apache.maven.lifecycle.internal.MojoExecutor.execute(MojoExecutor.java:145)\nat org.apache.maven.lifecycle.internal.LifecycleModuleBuilder.buildProject(LifecycleModuleBuilder.java:84)\nat org.apache.maven.lifecycle.internal.LifecycleModuleBuilder.buildProject(LifecycleModuleBuilder.java:59)\nat org.apache.maven.lifecycle.internal.LifecycleStarter.singleThreadedBuild(LifecycleStarter.java:183)\nat org.apache.maven.lifecycle.internal.LifecycleStarter.execute(LifecycleStarter.java:161)\nat org.apache.maven.DefaultMaven.doExecute(DefaultMaven.java:319)\nat org.apache.maven.DefaultMaven.execute(DefaultMaven.java:156)\nat org.apache.maven.cli.MavenCli.execute(MavenCli.java:537)\nat org.apache.maven.cli.MavenCli.doMain(MavenCli.java:196)\nat org.apache.maven.cli.MavenCli.main(MavenCli.java:141)\nat sun.reflect.NativeMethodAccessorImpl.invoke0(Native Method)\nat sun.reflect.NativeMethodAccessorImpl.invoke(NativeMethodAccessorImpl.java:39)\nat sun.reflect.DelegatingMethodAccessorImpl.invoke(DelegatingMethodAccessorImpl.java:25)\nat java.lang.reflect.Method.invoke(Method.java:597)\nat org.codehaus.plexus.classworlds.launcher.Launcher.launchEnhanced(Launcher.java:290)\nat org.codehaus.plexus.classworlds.launcher.Launcher.launch(Launcher.java:230)\nat org.codehaus.plexus.classworlds.launcher.Launcher.mainWithExitCode(Launcher.java:409)\nat org.codehaus.plexus.classworlds.launcher.Launcher.main(Launcher.java:352)\n```\n\nCaused by: org.apache.maven.plugin.compiler.CompilationFailureException: Compilation failure\nAn unknown compilation problem occurred\n\n```\nat org.apache.maven.plugin.compiler.AbstractCompilerMojo.execute(AbstractCompilerMojo.java:745)\nat org.apache.maven.plugin.compiler.TestCompilerMojo.execute(TestCompilerMojo.java:152)\nat org.apache.maven.plugin.DefaultBuildPluginManager.executeMojo(DefaultBuildPluginManager.java:101)\nat org.apache.maven.lifecycle.internal.MojoExecutor.execute(MojoExecutor.java:209)\n... 19 more\n```\n", "reactions": {"url": "https://api.github.com/repos/spring-projects/spring-data-book/issues/6/reactions", "total_count": 0, "+1": 0, "-1": 0, "laugh": 0, "hooray": 0, "confused": 0, "heart": 0}, "author_association": "NONE"}], "commits": [], "pull_requests": [], "issue_comments": [{"url": "https://api.github.com/repos/spring-projects/spring-data-book/issues/comments/20632712", "body": "I am also using STS. I always run mvn from command line. This test failed: Failed to execute goal org.apache.maven.plugins:maven-compiler-plugin:3.0:testCompile (default-testCompile) \n", "reactions": {"url": "https://api.github.com/repos/spring-projects/spring-data-book/issues/comments/20632712/reactions", "total_count": 0, "+1": 0, "-1": 0, "laugh": 0, "hooray": 0, "confused": 0, "heart": 0}, "author_association": "NONE"}], "commit_comments": [], "review_comments": []}, "trisberg": {"issues": [], "commits": [{"url": "https://api.github.com/repos/spring-projects/spring-data-book/commits/1db59b77bea7139ee54a0bdb62c38e9cfc82c432", "message": "updating readme files"}, {"url": "https://api.github.com/repos/spring-projects/spring-data-book/commits/35ad0c1bb556d19f49b3d6a7347bd79f91c9e580", "message": "updating pom for batch examples to match release version of spring-hadoop\n\n- updating the readme instructions"}, {"url": "https://api.github.com/repos/spring-projects/spring-data-book/commits/8cd7cfaf8c3d823a55508ddbf523815e1257c4e7", "message": "updating pom for syslog streaming example to match release version of spring-hadoop\n\n- adding instructions for enabling (r)syslog to send to tcp/udp ports"}, {"url": "https://api.github.com/repos/spring-projects/spring-data-book/commits/3c2068bdf9dc4736e59bd711a3a1ab233c3f5bf2", "message": "updating pom for file polling and ftp examples to match release version of spring-hadoop"}, {"url": "https://api.github.com/repos/spring-projects/spring-data-book/commits/5040552fb152fa7ea3d02b185a16f87d547010f5", "message": "updating pom, config files and applicationContext for HBase examples to match release version of spring-hadoop"}, {"url": "https://api.github.com/repos/spring-projects/spring-data-book/commits/ab42b18239361ab1b657ce0da0e3d9acfbf96579", "message": "updating pom for Hadoop Pig examples to match release version of spring-hadoop"}, {"url": "https://api.github.com/repos/spring-projects/spring-data-book/commits/b9026bae99c39fe54486f73ccafabb06d78af72b", "message": "updating pom and applicationContext for Hadoop Hive examples to match release version of spring-hadoop"}, {"url": "https://api.github.com/repos/spring-projects/spring-data-book/commits/bb11d6a12a8dbc4ba9e27d528ca8a073ec42f3b2", "message": "updating pom and applicationContext for Hadoop scheduling examples to match release version of spring-hadoop"}, {"url": "https://api.github.com/repos/spring-projects/spring-data-book/commits/d02453ad48f5dbc939188e959d98b26a9f1f72cd", "message": "updating pom's for Hadoop wordcount examples with release version for spring-hadoop"}, {"url": "https://api.github.com/repos/spring-projects/spring-data-book/commits/9a4266b1b5b68e119b5bbdd5e684eb741afc4cd2", "message": "Upgraded to Spring Data JDBC Extensions 1.0.0.RELEASE"}, {"url": "https://api.github.com/repos/spring-projects/spring-data-book/commits/31b548271d20fae87f05d0b7422736eb45fef52c", "message": "Modifying Qyerydsl generation to use in-memory with db/init file"}, {"url": "https://api.github.com/repos/spring-projects/spring-data-book/commits/ef715fda795db8de3b3091ed03033bfe68a63b9c", "message": "Adding Roo example"}, {"url": "https://api.github.com/repos/spring-projects/spring-data-book/commits/75557575d0a5c6c2fb8ad512a41f9ebd3fedd644", "message": "Removing oracle example"}, {"url": "https://api.github.com/repos/spring-projects/spring-data-book/commits/e9fa64dea68d70772be01bc1377a15351312f449", "message": "Working on examples for Oracle"}, {"url": "https://api.github.com/repos/spring-projects/spring-data-book/commits/bbd6c430ed15d45e822be13a4071807169b55fbf", "message": "cleanup SQL"}, {"url": "https://api.github.com/repos/spring-projects/spring-data-book/commits/3f724256d66ebc2245a0e3239e20b8bdb0f2775f", "message": "Working on examples for Oracle"}, {"url": "https://api.github.com/repos/spring-projects/spring-data-book/commits/a6b7ff7a5eca796dcf9f9e78577b18d58f0d0d51", "message": "Working on examples for Oracle"}, {"url": "https://api.github.com/repos/spring-projects/spring-data-book/commits/f214922c5bf9048490eec9759fb05ad8a3f3a0ec", "message": "Adding equals and hashCode to EmailAddress"}, {"url": "https://api.github.com/repos/spring-projects/spring-data-book/commits/2fb1d6b6c3b7c1723724d257b4bd34a466f5270f", "message": "Working on examples for JDBC/Querydsl/Oracle"}, {"url": "https://api.github.com/repos/spring-projects/spring-data-book/commits/453afadb9733a9836bc8b2199dd11d8d02dadaa2", "message": "Working on examples for JDBC/Querydsl"}, {"url": "https://api.github.com/repos/spring-projects/spring-data-book/commits/150679459e67b15322e25b09809f39dfb3a07c87", "message": "Refactoring QueryDSL JDBC example and tests"}, {"url": "https://api.github.com/repos/spring-projects/spring-data-book/commits/da98bb22eca767c4314d8ee7fbb1711d0c3eaf39", "message": "Refactoring QueryDSL JDBC example and tests"}, {"url": "https://api.github.com/repos/spring-projects/spring-data-book/commits/9e34cd3e0671a6d5df4e079708abb9e57c6d7dd2", "message": "Splitting Oracle code into separate oracle module, adding jdbc to parent build"}, {"url": "https://api.github.com/repos/spring-projects/spring-data-book/commits/bcbbab3156f64b4d01cca7fd1a2952107f85214a", "message": "Updating QueryDSL JDBC example and tests"}, {"url": "https://api.github.com/repos/spring-projects/spring-data-book/commits/90badb18c566d3cf2412aa79c54da9d1a8353e1d", "message": "Adding QueryDSL JDBC example with database integration tests"}, {"url": "https://api.github.com/repos/spring-projects/spring-data-book/commits/5ee894ea3d54932e5f0c7a9cbd458bfce90a01fc", "message": "Adding unit test for HelloOracle"}, {"url": "https://api.github.com/repos/spring-projects/spring-data-book/commits/39ae01a905f2dbc02a11e18dfc900fc7a8f274ea", "message": "Inital code for Hello QueryDSL example"}, {"url": "https://api.github.com/repos/spring-projects/spring-data-book/commits/4fa8155800ddfa728c46823e27869be642e4d5f5", "message": "Inital code for Hello Oracle example"}, {"url": "https://api.github.com/repos/spring-projects/spring-data-book/commits/7fd51e20dc0d016f9c822132bd72a234c7e2097f", "message": "Build infrastructure for jdbc module.\n\nAdding necessary dependencies etc. to run the build as a standalone project."}, {"url": "https://api.github.com/repos/spring-projects/spring-data-book/commits/5f879363170d5b803cf1383cf56ee813c0518731", "message": "Adding repositories to resolve locally installed artifacts"}, {"url": "https://api.github.com/repos/spring-projects/spring-data-book/commits/f6155c25acfcf3787a63306b138959cfd37b8f44", "message": "Adding jdbc sub-project"}], "pull_requests": [], "issue_comments": [], "commit_comments": [], "review_comments": []}, "jexp": {"issues": [], "commits": [{"url": "https://api.github.com/repos/spring-projects/spring-data-book/commits/f58102875767bb8479c945f582bdbefb662252ac", "message": "added ratings and categories as book examples, added cypher-dsl/query-dsl example"}, {"url": "https://api.github.com/repos/spring-projects/spring-data-book/commits/d5dd1e23009044da3be14292258c6df218675d6e", "message": "made all Itegration Tests pass"}, {"url": "https://api.github.com/repos/spring-projects/spring-data-book/commits/886d941465338aa6d014625c004920a25aada7fc", "message": "initial commit SDN"}, {"url": "https://api.github.com/repos/spring-projects/spring-data-book/commits/c6c2c966ebbcd4090d5501f85791f8e891243c45", "message": "simplified customer, added date to order"}, {"url": "https://api.github.com/repos/spring-projects/spring-data-book/commits/a6ccc0493117bb6ec11e188b6f761b3c594bd615", "message": "removed zipcode from address"}, {"url": "https://api.github.com/repos/spring-projects/spring-data-book/commits/5ec2832ff1f92c20d84a999936cc95e0ee7b909b", "message": "added domain model drawing as PDF"}, {"url": "https://api.github.com/repos/spring-projects/spring-data-book/commits/b4f71e9bcd71c8489045b40df20cfc4640edf04e", "message": "added domain model drawing"}, {"url": "https://api.github.com/repos/spring-projects/spring-data-book/commits/87fb2bc351eafb153ad49db1584e2641adf91390", "message": "first commit"}], "pull_requests": [], "issue_comments": [], "commit_comments": [], "review_comments": []}, "dturanski": {"issues": [], "commits": [{"url": "https://api.github.com/repos/spring-projects/spring-data-book/commits/cd48be09762a77c69571dec4ad8ade3baefc2781", "message": "added comments to gemfire code"}, {"url": "https://api.github.com/repos/spring-projects/spring-data-book/commits/fcf06d687ee4993df23b31de846ee0311accc42b", "message": "Added CustomerDao example for gemfire"}, {"url": "https://api.github.com/repos/spring-projects/spring-data-book/commits/99d7a1a0aa2bf528b91904c499343a1ef255d690", "message": "Merge branch 'master' of https://github.com/SpringSource/spring-data-book"}, {"url": "https://api.github.com/repos/spring-projects/spring-data-book/commits/103c04d5e2770d945433940d611ad027bec14ebc", "message": "Clean up gemfire project"}, {"url": "https://api.github.com/repos/spring-projects/spring-data-book/commits/1b6f1272b13b7e7d0dfd7719777e4f7cc8bada72", "message": "cleaned up pom formatting and added vf* to .gitignore"}, {"url": "https://api.github.com/repos/spring-projects/spring-data-book/commits/e79e6994d3612817e88cd616443dd10a93273f6d", "message": "added gemfire project"}], "pull_requests": [], "issue_comments": [{"url": "https://api.github.com/repos/spring-projects/spring-data-book/issues/comments/14616822", "body": "This is a benign message. Note that it's a warning message. Gemfire does not throw the exception, merely logs it.\n", "reactions": {"url": "https://api.github.com/repos/spring-projects/spring-data-book/issues/comments/14616822/reactions", "total_count": 0, "+1": 0, "-1": 0, "laugh": 0, "hooray": 0, "confused": 0, "heart": 0}, "author_association": "MEMBER"}, {"url": "https://api.github.com/repos/spring-projects/spring-data-book/issues/comments/14773791", "body": "Actually, I just made a change so that by default the RFB doesn't try to close the region in it's destroy method. It appears to be unnecessary, since GF takes care of this internally. I've left it as an option for now. \n", "reactions": {"url": "https://api.github.com/repos/spring-projects/spring-data-book/issues/comments/14773791/reactions", "total_count": 0, "+1": 0, "-1": 0, "laugh": 0, "hooray": 0, "confused": 0, "heart": 0}, "author_association": "MEMBER"}], "commit_comments": [], "review_comments": []}, "jbrisbin": {"issues": [], "commits": [{"url": "https://api.github.com/repos/spring-projects/spring-data-book/commits/b68b25b6cbd43d8c7b2ce0b97eb1e332661e0290", "message": "More example code for Redis chapter covering PubSub and Caching."}, {"url": "https://api.github.com/repos/spring-projects/spring-data-book/commits/4bbe29f003b5eaf534bff990569133798fa7e3bf", "message": "Removed some IDEA files"}, {"url": "https://api.github.com/repos/spring-projects/spring-data-book/commits/76bb5892cab707cae862b4590f8032b14d3cf8ad", "message": "Had to add stub package-info files to get directories to show up in git"}, {"url": "https://api.github.com/repos/spring-projects/spring-data-book/commits/369d18e11579acb28e7e145873d2e890063193e1", "message": "Initial commit of gradle project"}], "pull_requests": [], "issue_comments": [], "commit_comments": [], "review_comments": []}, "elharo": {"issues": [], "commits": [], "pull_requests": [{"url": "https://api.github.com/repos/spring-projects/spring-data-book/pulls/19", "title": "Upgrade Apache Commons Collections to v3.2.2", "body": "Version 3.2.1 has a CVSS 10.0 vulnerability. That's the worst kind of\nvulnerability that exists. By merely existing on the classpath, this\nlibrary causes the Java serialization parser for the entire JVM process\nto go from being a state machine to a turing machine. A turing machine\nwith an exec() function!\n\nhttps://web.nvd.nist.gov/view/vuln/detail?vulnId=CVE-2015-8103\nhttps://commons.apache.org/proper/commons-collections/security-reports.html\nhttp://foxglovesecurity.com/2015/11/06/what-do-weblogic-websphere-jboss-jenkins-opennms-and-your-application-have-in-common-this-vulnerability/\n", "author_association": "NONE"}], "issue_comments": [], "commit_comments": [], "review_comments": []}, "mnmami": {"issues": [], "commits": [], "pull_requests": [{"url": "https://api.github.com/repos/spring-projects/spring-data-book/pulls/13", "title": "Simple formatting :)", "body": "Some programmers, me included, just can't read well formatted code.\n", "author_association": "NONE"}], "issue_comments": [], "commit_comments": [], "review_comments": []}, "zhouwenbo": {"issues": [], "commits": [], "pull_requests": [{"url": "https://api.github.com/repos/spring-projects/spring-data-book/pulls/12", "title": "Update pom.xml", "body": "update\n", "author_association": "NONE"}], "issue_comments": [{"url": "https://api.github.com/repos/spring-projects/spring-data-book/issues/comments/46516613", "body": "gggg\n", "reactions": {"url": "https://api.github.com/repos/spring-projects/spring-data-book/issues/comments/46516613/reactions", "total_count": 0, "+1": 0, "-1": 0, "laugh": 0, "hooray": 0, "confused": 0, "heart": 0}, "author_association": "NONE"}, {"url": "https://api.github.com/repos/spring-projects/spring-data-book/issues/comments/46516636", "body": "this is update\n", "reactions": {"url": "https://api.github.com/repos/spring-projects/spring-data-book/issues/comments/46516636/reactions", "total_count": 0, "+1": 0, "-1": 0, "laugh": 0, "hooray": 0, "confused": 0, "heart": 0}, "author_association": "NONE"}], "commit_comments": [], "review_comments": []}, "a3692468": {"issues": [], "commits": [], "pull_requests": [{"url": "https://api.github.com/repos/spring-projects/spring-data-book/pulls/5", "title": "Update pom.xml", "body": "With\u00a0<spring.hadoop.version>1.0.0.BUILD-SNAPSHOT</spring.hadoop.version>\nthis project doesn't compile. Updating to 1.0.0.RELEASE does.\n", "author_association": "NONE"}], "issue_comments": [], "commit_comments": [], "review_comments": []}, "jotomo": {"issues": [], "commits": [], "pull_requests": [], "issue_comments": [{"url": "https://api.github.com/repos/spring-projects/spring-data-book/issues/comments/8950822", "body": "Neat. Why didn't I think of that? ;-)\nI can confirm that it works.\nThanks Oliver!\n", "reactions": {"url": "https://api.github.com/repos/spring-projects/spring-data-book/issues/comments/8950822/reactions", "total_count": 0, "+1": 0, "-1": 0, "laugh": 0, "hooray": 0, "confused": 0, "heart": 0}, "author_association": "NONE"}, {"url": "https://api.github.com/repos/spring-projects/spring-data-book/issues/comments/8956650", "body": "The book states that @EnableJpaRepositories \"includes\" the @ComponentScan as well as the @EnableTransactionManagement annotations. Thus the @EnableTransactionManagement annotation should be in PlainJpaConfig instead of InfastructureConfig, as the Spring Data JPA configuration doesn't need it. Other than the book I haven't seen a hint that @EnableJpaRepositories includes those two other annotations, which makes it tricky to understand what's going. However, that could be just me still learning and reading through Spring documentation. Also, as the book mentions, any non-small application will probably use all those annotation anyhow, so I might be overthinking this.\n\nOn a related note, what is the advantage of @Import over just extending the base Infastructure class? The later seems simpler and more intuitive to understand to me. Both approaches seem to work and I couldn't found any documentation on why @Import would be preferably (other than allowing to specify more than one class, as would be the limitation when extending. Hm, that's probably my answer).\n", "reactions": {"url": "https://api.github.com/repos/spring-projects/spring-data-book/issues/comments/8956650/reactions", "total_count": 0, "+1": 0, "-1": 0, "laugh": 0, "hooray": 0, "confused": 0, "heart": 0}, "author_association": "NONE"}], "commit_comments": [], "review_comments": []}, "topchimp": {"issues": [], "commits": [], "pull_requests": [], "issue_comments": [{"url": "https://api.github.com/repos/spring-projects/spring-data-book/issues/comments/14613748", "body": "Good luck @a3692468  - mine has been waiting since December...\n", "reactions": {"url": "https://api.github.com/repos/spring-projects/spring-data-book/issues/comments/14613748/reactions", "total_count": 0, "+1": 0, "-1": 0, "laugh": 0, "hooray": 0, "confused": 0, "heart": 0}, "author_association": "NONE"}], "commit_comments": [], "review_comments": []}, "moozungu": {"issues": [], "commits": [], "pull_requests": [], "issue_comments": [{"url": "https://api.github.com/repos/spring-projects/spring-data-book/issues/comments/20624039", "body": "I have gotten the same issue and have tried numerous updates.  \n\nthysmichels :  Were you able to continue running projects from your Eclipse IDE, (I am using STS) even though you were getting this error.\n\nHas anyone else been able to overcome this error? I wish there was a bit more direction in setting these examples up? Using Maven Clean Install and then importing project in to STS. However, I really don't understand how to run the examples from STS IDE... any direction would be helpful and I would be tremendously thankful.\n", "reactions": {"url": "https://api.github.com/repos/spring-projects/spring-data-book/issues/comments/20624039/reactions", "total_count": 0, "+1": 0, "-1": 0, "laugh": 0, "hooray": 0, "confused": 0, "heart": 0}, "author_association": "NONE"}], "commit_comments": [], "review_comments": []}, "thomasdarimont": {"issues": [], "commits": [], "pull_requests": [], "issue_comments": [{"url": "https://api.github.com/repos/spring-projects/spring-data-book/issues/comments/22167967", "body": "Hello,\n\nis this still an issue?\nI can do a git clone & mvn clean package on a OSX as well as on a Windows box.\n\nCheers,\nThomas\n", "reactions": {"url": "https://api.github.com/repos/spring-projects/spring-data-book/issues/comments/22167967/reactions", "total_count": 0, "+1": 0, "-1": 0, "laugh": 0, "hooray": 0, "confused": 0, "heart": 0}, "author_association": "NONE"}], "commit_comments": [], "review_comments": []}, "sportingkcfan": {"issues": [], "commits": [], "pull_requests": [], "issue_comments": [{"url": "https://api.github.com/repos/spring-projects/spring-data-book/issues/comments/22265286", "body": "Yes, this is still an issue for me as well.\n", "reactions": {"url": "https://api.github.com/repos/spring-projects/spring-data-book/issues/comments/22265286/reactions", "total_count": 0, "+1": 0, "-1": 0, "laugh": 0, "hooray": 0, "confused": 0, "heart": 0}, "author_association": "NONE"}], "commit_comments": [], "review_comments": []}, "batratanuj": {"issues": [], "commits": [], "pull_requests": [], "issue_comments": [{"url": "https://api.github.com/repos/spring-projects/spring-data-book/issues/comments/28483546", "body": "I am also facing this issue. Any resolution for this?\n", "reactions": {"url": "https://api.github.com/repos/spring-projects/spring-data-book/issues/comments/28483546/reactions", "total_count": 0, "+1": 0, "-1": 0, "laugh": 0, "hooray": 0, "confused": 0, "heart": 0}, "author_association": "NONE"}], "commit_comments": [], "review_comments": []}, "corneil": {"issues": [], "commits": [], "pull_requests": [], "issue_comments": [{"url": "https://api.github.com/repos/spring-projects/spring-data-book/issues/comments/74512446", "body": "The classes QCustomer and QProduct are generated by QueryDSL.\n\nOn 15 February 2015 at 08:14, moke110007 notifications@github.com wrote:\n\n> 1. QCustomer cannot be resolved to a type\n>    1. QProduct cannot be resolved to a type\n> \n> \u2014\n> Reply to this email directly or view it on GitHub\n> https://github.com/spring-projects/spring-data-book/issues/15.\n", "reactions": {"url": "https://api.github.com/repos/spring-projects/spring-data-book/issues/comments/74512446/reactions", "total_count": 0, "+1": 0, "-1": 0, "laugh": 0, "hooray": 0, "confused": 0, "heart": 0}, "author_association": "NONE"}, {"url": "https://api.github.com/repos/spring-projects/spring-data-book/issues/comments/87464867", "body": "How are you building your project?\nIs your IDE reporting the error or is your build system reporting the error?\n\nOn 29 March 2015 at 20:28, Alexander Golonzovsky notifications@github.com\nwrote:\n\n> I'm also having this issue with latest sources, seems neo4j-cypher-dsl\n> artifact v1.8 cant be fetched.\n> Strange, as I can see\n> http://m2.neo4j.org/service/local/repositories/releases/content/org/neo4j/neo4j-cypher-dsl/1.8/neo4j-cypher-dsl-1.8.jar\n> it in http://m2.neo4j.org/releases.\n> \n> [WARNING] The POM for org.neo4j:neo4j-cypher-dsl:jar:1.8 is missing, no dependency information available\n> Downloading: http://m2.neo4j.org/releases/org/neo4j/neo4j-cypher-dsl/1.8/neo4j-cypher-dsl-1.8.jar\n> Downloading: http://repo.maven.apache.org/maven2/org/neo4j/neo4j-cypher-dsl/1.8/neo4j-cypher-dsl-1.8.jar\n> \n> \u2014\n> Reply to this email directly or view it on GitHub\n> https://github.com/spring-projects/spring-data-book/issues/15#issuecomment-87453713\n> .\n", "reactions": {"url": "https://api.github.com/repos/spring-projects/spring-data-book/issues/comments/87464867/reactions", "total_count": 0, "+1": 0, "-1": 0, "laugh": 0, "hooray": 0, "confused": 0, "heart": 0}, "author_association": "NONE"}], "commit_comments": [], "review_comments": []}, "golonzovsky": {"issues": [], "commits": [], "pull_requests": [], "issue_comments": [{"url": "https://api.github.com/repos/spring-projects/spring-data-book/issues/comments/87453713", "body": "I'm also having this issue with latest sources, seems neo4j-cypher-dsl artifact v1.8 cant be fetched. \nStrange, as I can [see](http://m2.neo4j.org/service/local/repositories/releases/content/org/neo4j/neo4j-cypher-dsl/1.8/neo4j-cypher-dsl-1.8.jar) it in [nexus](http://m2.neo4j.org/index.html#view-repositories;releases~browsestorage)\n\n```\n[WARNING] The POM for org.neo4j:neo4j-cypher-dsl:jar:1.8 is missing, no dependency information available\nDownloading: http://m2.neo4j.org/releases/org/neo4j/neo4j-cypher-dsl/1.8/neo4j-cypher-dsl-1.8.jar\nDownloading: http://repo.maven.apache.org/maven2/org/neo4j/neo4j-cypher-dsl/1.8/neo4j-cypher-dsl-1.8.jar\n```\n\nUPD: seems some issues with their repo (and 1.8 is not in maven central yet). As a workaround you may install jar locally\n\n```\nmvn install:install-file -Dfile=neo4j-cypher-dsl-1.8.jar -DgroupId=org.neo4j -DartifactId=neo4j-cypher-dsl -Dversion=1.8 -Dpackaging=jar\n```\n", "reactions": {"url": "https://api.github.com/repos/spring-projects/spring-data-book/issues/comments/87453713/reactions", "total_count": 0, "+1": 0, "-1": 0, "laugh": 0, "hooray": 0, "confused": 0, "heart": 0}, "author_association": "NONE"}, {"url": "https://api.github.com/repos/spring-projects/spring-data-book/issues/comments/87473675", "body": "Both actually, below is _mvn clean install_ output (after deleting manually installed jar from .m2):\n\n```\nC:\\_dev\\_projects\\spring-data-book\\neo4j>mvn clean install\n[INFO] Scanning for projects...\n[INFO]\n[INFO] ------------------------------------------------------------------------\n[INFO] Building Spring Data Book - Neo4J 1.0.0.BUILD-SNAPSHOT\n[INFO] ------------------------------------------------------------------------\n[WARNING] The POM for org.neo4j:neo4j-cypher-dsl:jar:1.8 is missing, no dependency information available\n[INFO] ------------------------------------------------------------------------\n[INFO] BUILD FAILURE\n[INFO] ------------------------------------------------------------------------\n[INFO] Total time: 0.729 s\n[INFO] Finished at: 2015-03-29T22:40:39+02:00\n[INFO] Final Memory: 8M/308M\n[INFO] ------------------------------------------------------------------------\n[ERROR] Failed to execute goal on project spring-data-book-neo4j: Could not resolve dependencies for project com.oreilly.springdata:spring-data-book-neo4j:jar:1.0.0.BUILD-SNAPSHOT: Failure to find org.neo4j:neo4j-cypher-dsl:jar:1.8 in http://m2.neo4j.org/releases was cached in the local repository, resolution will not be reattempted until the update interval of neo4j-public-release-repository has elapsed or updates are forced -> [Help 1]\n[ERROR]\n[ERROR] To see the full stack trace of the errors, re-run Maven with the -e switch.\n[ERROR] Re-run Maven using the -X switch to enable full debug logging.\n[ERROR]\n[ERROR] For more information about the errors and possible solutions, please read the following articles:\n[ERROR] [Help 1] http://cwiki.apache.org/confluence/display/MAVEN/DependencyResolutionException\n```\n", "reactions": {"url": "https://api.github.com/repos/spring-projects/spring-data-book/issues/comments/87473675/reactions", "total_count": 0, "+1": 0, "-1": 0, "laugh": 0, "hooray": 0, "confused": 0, "heart": 0}, "author_association": "NONE"}], "commit_comments": [], "review_comments": []}, "gabhi": {"issues": [], "commits": [], "pull_requests": [], "issue_comments": [{"url": "https://api.github.com/repos/spring-projects/spring-data-book/issues/comments/146367706", "body": "+1\n", "reactions": {"url": "https://api.github.com/repos/spring-projects/spring-data-book/issues/comments/146367706/reactions", "total_count": 0, "+1": 0, "-1": 0, "laugh": 0, "hooray": 0, "confused": 0, "heart": 0}, "author_association": "NONE"}], "commit_comments": [], "review_comments": []}, "ycyyww": {"issues": [], "commits": [], "pull_requests": [], "issue_comments": [{"url": "https://api.github.com/repos/spring-projects/spring-data-book/issues/comments/172803131", "body": "i have a same exception like you. Do you resolve this problem?\n", "reactions": {"url": "https://api.github.com/repos/spring-projects/spring-data-book/issues/comments/172803131/reactions", "total_count": 0, "+1": 0, "-1": 0, "laugh": 0, "hooray": 0, "confused": 0, "heart": 0}, "author_association": "NONE"}], "commit_comments": [], "review_comments": []}, "phxism": {"issues": [], "commits": [], "pull_requests": [], "issue_comments": [{"url": "https://api.github.com/repos/spring-projects/spring-data-book/issues/comments/174810830", "body": "+1\n", "reactions": {"url": "https://api.github.com/repos/spring-projects/spring-data-book/issues/comments/174810830/reactions", "total_count": 0, "+1": 0, "-1": 0, "laugh": 0, "hooray": 0, "confused": 0, "heart": 0}, "author_association": "NONE"}], "commit_comments": [], "review_comments": []}, "odin88": {"issues": [], "commits": [], "pull_requests": [], "issue_comments": [{"url": "https://api.github.com/repos/spring-projects/spring-data-book/issues/comments/218485295", "body": "Might want to check this http://stackoverflow.com/a/32556217\n", "reactions": {"url": "https://api.github.com/repos/spring-projects/spring-data-book/issues/comments/218485295/reactions", "total_count": 0, "+1": 0, "-1": 0, "laugh": 0, "hooray": 0, "confused": 0, "heart": 0}, "author_association": "NONE"}], "commit_comments": [], "review_comments": []}, "JannoTilk": {"issues": [], "commits": [], "pull_requests": [], "issue_comments": [{"url": "https://api.github.com/repos/spring-projects/spring-data-book/issues/comments/240429747", "body": "I have got exactly the same problem. Has anyone found solution?\nIntelliJ 15.0.3 Win 10 Pro\n", "reactions": {"url": "https://api.github.com/repos/spring-projects/spring-data-book/issues/comments/240429747/reactions", "total_count": 0, "+1": 0, "-1": 0, "laugh": 0, "hooray": 0, "confused": 0, "heart": 0}, "author_association": "NONE"}], "commit_comments": [], "review_comments": []}, "faissalwise": {"issues": [], "commits": [], "pull_requests": [], "issue_comments": [{"url": "https://api.github.com/repos/spring-projects/spring-data-book/issues/comments/250435017", "body": "It's just a compilation problem,we must compile your project with the JDK 6.So make sure we use the appropriate compiler version.\n", "reactions": {"url": "https://api.github.com/repos/spring-projects/spring-data-book/issues/comments/250435017/reactions", "total_count": 0, "+1": 0, "-1": 0, "laugh": 0, "hooray": 0, "confused": 0, "heart": 0}, "author_association": "NONE"}], "commit_comments": [], "review_comments": []}, "acohen1644": {"issues": [], "commits": [], "pull_requests": [], "issue_comments": [{"url": "https://api.github.com/repos/spring-projects/spring-data-book/issues/comments/253711899", "body": "@dhluong90 , I'm getting exactly this error when I run \"mvn clean package\" as described in Chapter 1 of \"Spring Data.\" Did you find a way to avoid this error? \n", "reactions": {"url": "https://api.github.com/repos/spring-projects/spring-data-book/issues/comments/253711899/reactions", "total_count": 0, "+1": 0, "-1": 0, "laugh": 0, "hooray": 0, "confused": 0, "heart": 0}, "author_association": "NONE"}, {"url": "https://api.github.com/repos/spring-projects/spring-data-book/issues/comments/253852025", "body": "I'm using a system whose security constraints make it difficult for me to install another JDK. Is there some way to make this work with JDK 8?\n", "reactions": {"url": "https://api.github.com/repos/spring-projects/spring-data-book/issues/comments/253852025/reactions", "total_count": 0, "+1": 0, "-1": 0, "laugh": 0, "hooray": 0, "confused": 0, "heart": 0}, "author_association": "NONE"}], "commit_comments": [], "review_comments": []}, "pogoretska": {"issues": [], "commits": [], "pull_requests": [], "issue_comments": [{"url": "https://api.github.com/repos/spring-projects/spring-data-book/issues/comments/254159620", "body": "Tests are failing; when skipping them, got an\n\n[ERROR] Failed to execute goal on project spring-data-book-neo4j: Could not resolve dependencies for project com.oreilly.springdata:spring-data-book-neo4j:jar:1.0.0.BUILD-SNAPSHOT: Could not find artifact org.neo4j:neo4j-cypher-dsl:jar:1.8 in neo4j-public-release-repository (http://m2.neo4j.org/releases) -> [Help 1]\n", "reactions": {"url": "https://api.github.com/repos/spring-projects/spring-data-book/issues/comments/254159620/reactions", "total_count": 0, "+1": 0, "-1": 0, "laugh": 0, "hooray": 0, "confused": 0, "heart": 0}, "author_association": "NONE"}], "commit_comments": [], "review_comments": []}, "VonUniGE": {"issues": [], "commits": [], "pull_requests": [], "issue_comments": [{"url": "https://api.github.com/repos/spring-projects/spring-data-book/issues/comments/262956250", "body": "Last commit is from 9 Apr 2013. Is this project still officially supported?", "reactions": {"url": "https://api.github.com/repos/spring-projects/spring-data-book/issues/comments/262956250/reactions", "total_count": 0, "+1": 0, "-1": 0, "laugh": 0, "hooray": 0, "confused": 0, "heart": 0}, "author_association": "NONE"}], "commit_comments": [], "review_comments": []}, "pivotal-issuemaster": {"issues": [], "commits": [], "pull_requests": [], "issue_comments": [{"url": "https://api.github.com/repos/spring-projects/spring-data-book/issues/comments/271291216", "body": "@elharo Please sign the [Contributor License Agreement](https://cla.pivotal.io/sign/spring)!\n\n[Click here](https://cla.pivotal.io/sync/spring?repositoryId=spring-projects/spring-data-book&pullRequestId=19) to manually synchronize the status of this Pull Request.\n\nSee the [FAQ](https://cla.pivotal.io/faq) for frequently asked questions.", "reactions": {"url": "https://api.github.com/repos/spring-projects/spring-data-book/issues/comments/271291216/reactions", "total_count": 0, "+1": 0, "-1": 0, "laugh": 0, "hooray": 0, "confused": 0, "heart": 0}, "author_association": "NONE"}, {"url": "https://api.github.com/repos/spring-projects/spring-data-book/issues/comments/271291222", "body": "@mnmami Please sign the [Contributor License Agreement](https://cla.pivotal.io/sign/spring)!\n\n[Click here](https://cla.pivotal.io/sync/spring?repositoryId=spring-projects/spring-data-book&pullRequestId=13) to manually synchronize the status of this Pull Request.\n\nSee the [FAQ](https://cla.pivotal.io/faq) for frequently asked questions.", "reactions": {"url": "https://api.github.com/repos/spring-projects/spring-data-book/issues/comments/271291222/reactions", "total_count": 0, "+1": 0, "-1": 0, "laugh": 0, "hooray": 0, "confused": 0, "heart": 0}, "author_association": "NONE"}, {"url": "https://api.github.com/repos/spring-projects/spring-data-book/issues/comments/271291232", "body": "@zhouwenbo Please sign the [Contributor License Agreement](https://cla.pivotal.io/sign/spring)!\n\n[Click here](https://cla.pivotal.io/sync/spring?repositoryId=spring-projects/spring-data-book&pullRequestId=12) to manually synchronize the status of this Pull Request.\n\nSee the [FAQ](https://cla.pivotal.io/faq) for frequently asked questions.", "reactions": {"url": "https://api.github.com/repos/spring-projects/spring-data-book/issues/comments/271291232/reactions", "total_count": 0, "+1": 0, "-1": 0, "laugh": 0, "hooray": 0, "confused": 0, "heart": 0}, "author_association": "NONE"}, {"url": "https://api.github.com/repos/spring-projects/spring-data-book/issues/comments/271291240", "body": "@a3692468 Please sign the [Contributor License Agreement](https://cla.pivotal.io/sign/spring)!\n\n[Click here](https://cla.pivotal.io/sync/spring?repositoryId=spring-projects/spring-data-book&pullRequestId=5) to manually synchronize the status of this Pull Request.\n\nSee the [FAQ](https://cla.pivotal.io/faq) for frequently asked questions.", "reactions": {"url": "https://api.github.com/repos/spring-projects/spring-data-book/issues/comments/271291240/reactions", "total_count": 0, "+1": 0, "-1": 0, "laugh": 0, "hooray": 0, "confused": 0, "heart": 0}, "author_association": "NONE"}], "commit_comments": [], "review_comments": []}, "yls705048720": {"issues": [], "commits": [], "pull_requests": [], "issue_comments": [{"url": "https://api.github.com/repos/spring-projects/spring-data-book/issues/comments/277930176", "body": "+1", "reactions": {"url": "https://api.github.com/repos/spring-projects/spring-data-book/issues/comments/277930176/reactions", "total_count": 0, "+1": 0, "-1": 0, "laugh": 0, "hooray": 0, "confused": 0, "heart": 0}, "author_association": "NONE"}], "commit_comments": [], "review_comments": []}, "erpaoshouling": {"issues": [], "commits": [], "pull_requests": [], "issue_comments": [{"url": "https://api.github.com/repos/spring-projects/spring-data-book/issues/comments/321959396", "body": "+1", "reactions": {"url": "https://api.github.com/repos/spring-projects/spring-data-book/issues/comments/321959396/reactions", "total_count": 0, "+1": 0, "-1": 0, "laugh": 0, "hooray": 0, "confused": 0, "heart": 0}, "author_association": "NONE"}], "commit_comments": [], "review_comments": []}, "liting-zhang": {"issues": [], "commits": [], "pull_requests": [], "issue_comments": [{"url": "https://api.github.com/repos/spring-projects/spring-data-book/issues/comments/328041492", "body": "+1", "reactions": {"url": "https://api.github.com/repos/spring-projects/spring-data-book/issues/comments/328041492/reactions", "total_count": 0, "+1": 0, "-1": 0, "laugh": 0, "hooray": 0, "confused": 0, "heart": 0}, "author_association": "NONE"}], "commit_comments": [], "review_comments": []}}}}