{"_default": {"1": {"issues": [{"url": "https://api.github.com/repos/os6sense/sunra_ffs_relay/issues/2", "repository_url": "https://api.github.com/repos/os6sense/sunra_ffs_relay", "labels_url": "https://api.github.com/repos/os6sense/sunra_ffs_relay/issues/2/labels{/name}", "comments_url": "https://api.github.com/repos/os6sense/sunra_ffs_relay/issues/2/comments", "events_url": "https://api.github.com/repos/os6sense/sunra_ffs_relay/issues/2/events", "html_url": "https://github.com/os6sense/sunra_ffs_relay/issues/2", "id": 65684674, "number": 2, "title": "ffserver is listed as running even when it isnt when checking status", "user": {"login": "os6sense", "id": 934066, "avatar_url": "https://avatars3.githubusercontent.com/u/934066?v=4", "gravatar_id": "", "url": "https://api.github.com/users/os6sense", "html_url": "https://github.com/os6sense", "followers_url": "https://api.github.com/users/os6sense/followers", "following_url": "https://api.github.com/users/os6sense/following{/other_user}", "gists_url": "https://api.github.com/users/os6sense/gists{/gist_id}", "starred_url": "https://api.github.com/users/os6sense/starred{/owner}{/repo}", "subscriptions_url": "https://api.github.com/users/os6sense/subscriptions", "organizations_url": "https://api.github.com/users/os6sense/orgs", "repos_url": "https://api.github.com/users/os6sense/repos", "events_url": "https://api.github.com/users/os6sense/events{/privacy}", "received_events_url": "https://api.github.com/users/os6sense/received_events", "type": "User", "site_admin": false}, "labels": [{"id": 131631941, "url": "https://api.github.com/repos/os6sense/sunra_ffs_relay/labels/bug", "name": "bug", "color": "fc2929", "default": true}], "state": "open", "locked": false, "assignee": {"login": "os6sense", "id": 934066, "avatar_url": "https://avatars3.githubusercontent.com/u/934066?v=4", "gravatar_id": "", "url": "https://api.github.com/users/os6sense", "html_url": "https://github.com/os6sense", "followers_url": "https://api.github.com/users/os6sense/followers", "following_url": "https://api.github.com/users/os6sense/following{/other_user}", "gists_url": "https://api.github.com/users/os6sense/gists{/gist_id}", "starred_url": "https://api.github.com/users/os6sense/starred{/owner}{/repo}", "subscriptions_url": "https://api.github.com/users/os6sense/subscriptions", "organizations_url": "https://api.github.com/users/os6sense/orgs", "repos_url": "https://api.github.com/users/os6sense/repos", "events_url": "https://api.github.com/users/os6sense/events{/privacy}", "received_events_url": "https://api.github.com/users/os6sense/received_events", "type": "User", "site_admin": false}, "assignees": [{"login": "os6sense", "id": 934066, "avatar_url": "https://avatars3.githubusercontent.com/u/934066?v=4", "gravatar_id": "", "url": "https://api.github.com/users/os6sense", "html_url": "https://github.com/os6sense", "followers_url": "https://api.github.com/users/os6sense/followers", "following_url": "https://api.github.com/users/os6sense/following{/other_user}", "gists_url": "https://api.github.com/users/os6sense/gists{/gist_id}", "starred_url": "https://api.github.com/users/os6sense/starred{/owner}{/repo}", "subscriptions_url": "https://api.github.com/users/os6sense/subscriptions", "organizations_url": "https://api.github.com/users/os6sense/orgs", "repos_url": "https://api.github.com/users/os6sense/repos", "events_url": "https://api.github.com/users/os6sense/events{/privacy}", "received_events_url": "https://api.github.com/users/os6sense/received_events", "type": "User", "site_admin": false}], "milestone": null, "comments": 1, "created_at": "2015-04-01T13:30:23Z", "updated_at": "2015-04-01T13:36:39Z", "closed_at": null, "author_association": "OWNER", "body": "e.g:\n\nsowhat@Monk-RPC:/var/sunra/sunra_ffs_relay$ ps -edalf | grep ffserver\n0 S sowhat   15079 19346  0  80   0 -  3986 pipe_w 14:30 pts/1    00:00:00 grep --color=auto ffserver\n\nsowhat@Monk-RPC:/var/sunra/sunra_ffs_relay$ ./sunra_ffserver_relay.rb status\nI, [2015-04-01T14:31:02.135927 #15086]  INFO -- : FFServer is Running!\n", "reactions": {"url": "https://api.github.com/repos/os6sense/sunra_ffs_relay/issues/2/reactions", "total_count": 0, "+1": 0, "-1": 0, "laugh": 0, "hooray": 0, "confused": 0, "heart": 0}}], "commits": [{"sha": "1a9497b2658afd4c802ef8cd053f03871d52bd1a", "commit": {"author": {"name": "os6sense", "email": "leej@sowhatresearch.com", "date": "2015-04-01T13:21:34Z"}, "committer": {"name": "os6sense", "email": "leej@sowhatresearch.com", "date": "2015-04-01T13:21:34Z"}, "message": "The command to delete the lock file prior to killing the pids had been incorporated into one of the comments", "tree": {"sha": "32308b6bb4944dc0f5417fe04763ee2f0f0efb7f", "url": "https://api.github.com/repos/os6sense/sunra_ffs_relay/git/trees/32308b6bb4944dc0f5417fe04763ee2f0f0efb7f"}, "url": "https://api.github.com/repos/os6sense/sunra_ffs_relay/git/commits/1a9497b2658afd4c802ef8cd053f03871d52bd1a", "comment_count": 0, "verification": {"verified": false, "reason": "unsigned", "signature": null, "payload": null}}, "url": "https://api.github.com/repos/os6sense/sunra_ffs_relay/commits/1a9497b2658afd4c802ef8cd053f03871d52bd1a", "html_url": "https://github.com/os6sense/sunra_ffs_relay/commit/1a9497b2658afd4c802ef8cd053f03871d52bd1a", "comments_url": "https://api.github.com/repos/os6sense/sunra_ffs_relay/commits/1a9497b2658afd4c802ef8cd053f03871d52bd1a/comments", "author": {"login": "os6sense", "id": 934066, "avatar_url": "https://avatars3.githubusercontent.com/u/934066?v=4", "gravatar_id": "", "url": "https://api.github.com/users/os6sense", "html_url": "https://github.com/os6sense", "followers_url": "https://api.github.com/users/os6sense/followers", "following_url": "https://api.github.com/users/os6sense/following{/other_user}", "gists_url": "https://api.github.com/users/os6sense/gists{/gist_id}", "starred_url": "https://api.github.com/users/os6sense/starred{/owner}{/repo}", "subscriptions_url": "https://api.github.com/users/os6sense/subscriptions", "organizations_url": "https://api.github.com/users/os6sense/orgs", "repos_url": "https://api.github.com/users/os6sense/repos", "events_url": "https://api.github.com/users/os6sense/events{/privacy}", "received_events_url": "https://api.github.com/users/os6sense/received_events", "type": "User", "site_admin": false}, "committer": {"login": "os6sense", "id": 934066, "avatar_url": "https://avatars3.githubusercontent.com/u/934066?v=4", "gravatar_id": "", "url": "https://api.github.com/users/os6sense", "html_url": "https://github.com/os6sense", "followers_url": "https://api.github.com/users/os6sense/followers", "following_url": "https://api.github.com/users/os6sense/following{/other_user}", "gists_url": "https://api.github.com/users/os6sense/gists{/gist_id}", "starred_url": "https://api.github.com/users/os6sense/starred{/owner}{/repo}", "subscriptions_url": "https://api.github.com/users/os6sense/subscriptions", "organizations_url": "https://api.github.com/users/os6sense/orgs", "repos_url": "https://api.github.com/users/os6sense/repos", "events_url": "https://api.github.com/users/os6sense/events{/privacy}", "received_events_url": "https://api.github.com/users/os6sense/received_events", "type": "User", "site_admin": false}, "parents": [{"sha": "160599e239a593412536eea57d1e3a775c42e43c", "url": "https://api.github.com/repos/os6sense/sunra_ffs_relay/commits/160599e239a593412536eea57d1e3a775c42e43c", "html_url": "https://github.com/os6sense/sunra_ffs_relay/commit/160599e239a593412536eea57d1e3a775c42e43c"}]}, {"sha": "160599e239a593412536eea57d1e3a775c42e43c", "commit": {"author": {"name": "os6sense", "email": "leej@sowhatresearch.com", "date": "2015-03-12T17:21:07Z"}, "committer": {"name": "os6sense", "email": "leej@sowhatresearch.com", "date": "2015-03-12T17:21:07Z"}, "message": "Sunra utils use github version now", "tree": {"sha": "5cc36362ec2e0eeb1e0bcd8d0f53b15b93143053", "url": "https://api.github.com/repos/os6sense/sunra_ffs_relay/git/trees/5cc36362ec2e0eeb1e0bcd8d0f53b15b93143053"}, "url": "https://api.github.com/repos/os6sense/sunra_ffs_relay/git/commits/160599e239a593412536eea57d1e3a775c42e43c", "comment_count": 0, "verification": {"verified": false, "reason": "unsigned", "signature": null, "payload": null}}, "url": "https://api.github.com/repos/os6sense/sunra_ffs_relay/commits/160599e239a593412536eea57d1e3a775c42e43c", "html_url": "https://github.com/os6sense/sunra_ffs_relay/commit/160599e239a593412536eea57d1e3a775c42e43c", "comments_url": "https://api.github.com/repos/os6sense/sunra_ffs_relay/commits/160599e239a593412536eea57d1e3a775c42e43c/comments", "author": {"login": "os6sense", "id": 934066, "avatar_url": "https://avatars3.githubusercontent.com/u/934066?v=4", "gravatar_id": "", "url": "https://api.github.com/users/os6sense", "html_url": "https://github.com/os6sense", "followers_url": "https://api.github.com/users/os6sense/followers", "following_url": "https://api.github.com/users/os6sense/following{/other_user}", "gists_url": "https://api.github.com/users/os6sense/gists{/gist_id}", "starred_url": "https://api.github.com/users/os6sense/starred{/owner}{/repo}", "subscriptions_url": "https://api.github.com/users/os6sense/subscriptions", "organizations_url": "https://api.github.com/users/os6sense/orgs", "repos_url": "https://api.github.com/users/os6sense/repos", "events_url": "https://api.github.com/users/os6sense/events{/privacy}", "received_events_url": "https://api.github.com/users/os6sense/received_events", "type": "User", "site_admin": false}, "committer": {"login": "os6sense", "id": 934066, "avatar_url": "https://avatars3.githubusercontent.com/u/934066?v=4", "gravatar_id": "", "url": "https://api.github.com/users/os6sense", "html_url": "https://github.com/os6sense", "followers_url": "https://api.github.com/users/os6sense/followers", "following_url": "https://api.github.com/users/os6sense/following{/other_user}", "gists_url": "https://api.github.com/users/os6sense/gists{/gist_id}", "starred_url": "https://api.github.com/users/os6sense/starred{/owner}{/repo}", "subscriptions_url": "https://api.github.com/users/os6sense/subscriptions", "organizations_url": "https://api.github.com/users/os6sense/orgs", "repos_url": "https://api.github.com/users/os6sense/repos", "events_url": "https://api.github.com/users/os6sense/events{/privacy}", "received_events_url": "https://api.github.com/users/os6sense/received_events", "type": "User", "site_admin": false}, "parents": [{"sha": "64aae86ef3bad68552f2d613e826839e38dbd4e9", "url": "https://api.github.com/repos/os6sense/sunra_ffs_relay/commits/64aae86ef3bad68552f2d613e826839e38dbd4e9", "html_url": "https://github.com/os6sense/sunra_ffs_relay/commit/64aae86ef3bad68552f2d613e826839e38dbd4e9"}]}, {"sha": "64aae86ef3bad68552f2d613e826839e38dbd4e9", "commit": {"author": {"name": "os6sense", "email": "leej@sowhatresearch.com", "date": "2015-03-12T17:03:23Z"}, "committer": {"name": "os6sense", "email": "leej@sowhatresearch.com", "date": "2015-03-12T17:03:23Z"}, "message": "Sunra utils use github version now", "tree": {"sha": "1ea957099cd6ccacc85ee5f375019d5605e6dc03", "url": "https://api.github.com/repos/os6sense/sunra_ffs_relay/git/trees/1ea957099cd6ccacc85ee5f375019d5605e6dc03"}, "url": "https://api.github.com/repos/os6sense/sunra_ffs_relay/git/commits/64aae86ef3bad68552f2d613e826839e38dbd4e9", "comment_count": 0, "verification": {"verified": false, "reason": "unsigned", "signature": null, "payload": null}}, "url": "https://api.github.com/repos/os6sense/sunra_ffs_relay/commits/64aae86ef3bad68552f2d613e826839e38dbd4e9", "html_url": "https://github.com/os6sense/sunra_ffs_relay/commit/64aae86ef3bad68552f2d613e826839e38dbd4e9", "comments_url": "https://api.github.com/repos/os6sense/sunra_ffs_relay/commits/64aae86ef3bad68552f2d613e826839e38dbd4e9/comments", "author": {"login": "os6sense", "id": 934066, "avatar_url": "https://avatars3.githubusercontent.com/u/934066?v=4", "gravatar_id": "", "url": "https://api.github.com/users/os6sense", "html_url": "https://github.com/os6sense", "followers_url": "https://api.github.com/users/os6sense/followers", "following_url": "https://api.github.com/users/os6sense/following{/other_user}", "gists_url": "https://api.github.com/users/os6sense/gists{/gist_id}", "starred_url": "https://api.github.com/users/os6sense/starred{/owner}{/repo}", "subscriptions_url": "https://api.github.com/users/os6sense/subscriptions", "organizations_url": "https://api.github.com/users/os6sense/orgs", "repos_url": "https://api.github.com/users/os6sense/repos", "events_url": "https://api.github.com/users/os6sense/events{/privacy}", "received_events_url": "https://api.github.com/users/os6sense/received_events", "type": "User", "site_admin": false}, "committer": {"login": "os6sense", "id": 934066, "avatar_url": "https://avatars3.githubusercontent.com/u/934066?v=4", "gravatar_id": "", "url": "https://api.github.com/users/os6sense", "html_url": "https://github.com/os6sense", "followers_url": "https://api.github.com/users/os6sense/followers", "following_url": "https://api.github.com/users/os6sense/following{/other_user}", "gists_url": "https://api.github.com/users/os6sense/gists{/gist_id}", "starred_url": "https://api.github.com/users/os6sense/starred{/owner}{/repo}", "subscriptions_url": "https://api.github.com/users/os6sense/subscriptions", "organizations_url": "https://api.github.com/users/os6sense/orgs", "repos_url": "https://api.github.com/users/os6sense/repos", "events_url": "https://api.github.com/users/os6sense/events{/privacy}", "received_events_url": "https://api.github.com/users/os6sense/received_events", "type": "User", "site_admin": false}, "parents": [{"sha": "b4af54479b3039bdc6d7a82bef88e6265c2787f6", "url": "https://api.github.com/repos/os6sense/sunra_ffs_relay/commits/b4af54479b3039bdc6d7a82bef88e6265c2787f6", "html_url": "https://github.com/os6sense/sunra_ffs_relay/commit/b4af54479b3039bdc6d7a82bef88e6265c2787f6"}]}, {"sha": "b4af54479b3039bdc6d7a82bef88e6265c2787f6", "commit": {"author": {"name": "os6sense", "email": "leej@sowhatresearch.com", "date": "2015-03-12T16:41:12Z"}, "committer": {"name": "os6sense", "email": "leej@sowhatresearch.com", "date": "2015-03-12T16:41:12Z"}, "message": "Gemfile", "tree": {"sha": "92c1cec697280835a75dac913bc7f91add19a7cd", "url": "https://api.github.com/repos/os6sense/sunra_ffs_relay/git/trees/92c1cec697280835a75dac913bc7f91add19a7cd"}, "url": "https://api.github.com/repos/os6sense/sunra_ffs_relay/git/commits/b4af54479b3039bdc6d7a82bef88e6265c2787f6", "comment_count": 0, "verification": {"verified": false, "reason": "unsigned", "signature": null, "payload": null}}, "url": "https://api.github.com/repos/os6sense/sunra_ffs_relay/commits/b4af54479b3039bdc6d7a82bef88e6265c2787f6", "html_url": "https://github.com/os6sense/sunra_ffs_relay/commit/b4af54479b3039bdc6d7a82bef88e6265c2787f6", "comments_url": "https://api.github.com/repos/os6sense/sunra_ffs_relay/commits/b4af54479b3039bdc6d7a82bef88e6265c2787f6/comments", "author": {"login": "os6sense", "id": 934066, "avatar_url": "https://avatars3.githubusercontent.com/u/934066?v=4", "gravatar_id": "", "url": "https://api.github.com/users/os6sense", "html_url": "https://github.com/os6sense", "followers_url": "https://api.github.com/users/os6sense/followers", "following_url": "https://api.github.com/users/os6sense/following{/other_user}", "gists_url": "https://api.github.com/users/os6sense/gists{/gist_id}", "starred_url": "https://api.github.com/users/os6sense/starred{/owner}{/repo}", "subscriptions_url": "https://api.github.com/users/os6sense/subscriptions", "organizations_url": "https://api.github.com/users/os6sense/orgs", "repos_url": "https://api.github.com/users/os6sense/repos", "events_url": "https://api.github.com/users/os6sense/events{/privacy}", "received_events_url": "https://api.github.com/users/os6sense/received_events", "type": "User", "site_admin": false}, "committer": {"login": "os6sense", "id": 934066, "avatar_url": "https://avatars3.githubusercontent.com/u/934066?v=4", "gravatar_id": "", "url": "https://api.github.com/users/os6sense", "html_url": "https://github.com/os6sense", "followers_url": "https://api.github.com/users/os6sense/followers", "following_url": "https://api.github.com/users/os6sense/following{/other_user}", "gists_url": "https://api.github.com/users/os6sense/gists{/gist_id}", "starred_url": "https://api.github.com/users/os6sense/starred{/owner}{/repo}", "subscriptions_url": "https://api.github.com/users/os6sense/subscriptions", "organizations_url": "https://api.github.com/users/os6sense/orgs", "repos_url": "https://api.github.com/users/os6sense/repos", "events_url": "https://api.github.com/users/os6sense/events{/privacy}", "received_events_url": "https://api.github.com/users/os6sense/received_events", "type": "User", "site_admin": false}, "parents": [{"sha": "8d64e62bc73ce1835ebaed5daaa6b056935957d0", "url": "https://api.github.com/repos/os6sense/sunra_ffs_relay/commits/8d64e62bc73ce1835ebaed5daaa6b056935957d0", "html_url": "https://github.com/os6sense/sunra_ffs_relay/commit/8d64e62bc73ce1835ebaed5daaa6b056935957d0"}]}, {"sha": "8d64e62bc73ce1835ebaed5daaa6b056935957d0", "commit": {"author": {"name": "os6sense", "email": "leej@sowhatresearch.com", "date": "2015-03-12T16:40:27Z"}, "committer": {"name": "os6sense", "email": "leej@sowhatresearch.com", "date": "2015-03-12T16:40:27Z"}, "message": "Formatting", "tree": {"sha": "e6d4d99ff447ada35f11486c2f989865b48865e4", "url": "https://api.github.com/repos/os6sense/sunra_ffs_relay/git/trees/e6d4d99ff447ada35f11486c2f989865b48865e4"}, "url": "https://api.github.com/repos/os6sense/sunra_ffs_relay/git/commits/8d64e62bc73ce1835ebaed5daaa6b056935957d0", "comment_count": 0, "verification": {"verified": false, "reason": "unsigned", "signature": null, "payload": null}}, "url": "https://api.github.com/repos/os6sense/sunra_ffs_relay/commits/8d64e62bc73ce1835ebaed5daaa6b056935957d0", "html_url": "https://github.com/os6sense/sunra_ffs_relay/commit/8d64e62bc73ce1835ebaed5daaa6b056935957d0", "comments_url": "https://api.github.com/repos/os6sense/sunra_ffs_relay/commits/8d64e62bc73ce1835ebaed5daaa6b056935957d0/comments", "author": {"login": "os6sense", "id": 934066, "avatar_url": "https://avatars3.githubusercontent.com/u/934066?v=4", "gravatar_id": "", "url": "https://api.github.com/users/os6sense", "html_url": "https://github.com/os6sense", "followers_url": "https://api.github.com/users/os6sense/followers", "following_url": "https://api.github.com/users/os6sense/following{/other_user}", "gists_url": "https://api.github.com/users/os6sense/gists{/gist_id}", "starred_url": "https://api.github.com/users/os6sense/starred{/owner}{/repo}", "subscriptions_url": "https://api.github.com/users/os6sense/subscriptions", "organizations_url": "https://api.github.com/users/os6sense/orgs", "repos_url": "https://api.github.com/users/os6sense/repos", "events_url": "https://api.github.com/users/os6sense/events{/privacy}", "received_events_url": "https://api.github.com/users/os6sense/received_events", "type": "User", "site_admin": false}, "committer": {"login": "os6sense", "id": 934066, "avatar_url": "https://avatars3.githubusercontent.com/u/934066?v=4", "gravatar_id": "", "url": "https://api.github.com/users/os6sense", "html_url": "https://github.com/os6sense", "followers_url": "https://api.github.com/users/os6sense/followers", "following_url": "https://api.github.com/users/os6sense/following{/other_user}", "gists_url": "https://api.github.com/users/os6sense/gists{/gist_id}", "starred_url": "https://api.github.com/users/os6sense/starred{/owner}{/repo}", "subscriptions_url": "https://api.github.com/users/os6sense/subscriptions", "organizations_url": "https://api.github.com/users/os6sense/orgs", "repos_url": "https://api.github.com/users/os6sense/repos", "events_url": "https://api.github.com/users/os6sense/events{/privacy}", "received_events_url": "https://api.github.com/users/os6sense/received_events", "type": "User", "site_admin": false}, "parents": [{"sha": "35a8b6b3667bda7b97c010dd108ba8bb85dd4c37", "url": "https://api.github.com/repos/os6sense/sunra_ffs_relay/commits/35a8b6b3667bda7b97c010dd108ba8bb85dd4c37", "html_url": "https://github.com/os6sense/sunra_ffs_relay/commit/35a8b6b3667bda7b97c010dd108ba8bb85dd4c37"}]}, {"sha": "35a8b6b3667bda7b97c010dd108ba8bb85dd4c37", "commit": {"author": {"name": "Lee Jackson", "email": "leej@sowhatresearch.com", "date": "2014-11-03T12:10:22Z"}, "committer": {"name": "Lee Jackson", "email": "leej@sowhatresearch.com", "date": "2014-11-03T12:10:22Z"}, "message": "Some sanity edits - status was far too complex so I've split it up; lock_file pids are now delegated", "tree": {"sha": "787155c288f9ce88c98ea83699824c95c7f491aa", "url": "https://api.github.com/repos/os6sense/sunra_ffs_relay/git/trees/787155c288f9ce88c98ea83699824c95c7f491aa"}, "url": "https://api.github.com/repos/os6sense/sunra_ffs_relay/git/commits/35a8b6b3667bda7b97c010dd108ba8bb85dd4c37", "comment_count": 0, "verification": {"verified": false, "reason": "unsigned", "signature": null, "payload": null}}, "url": "https://api.github.com/repos/os6sense/sunra_ffs_relay/commits/35a8b6b3667bda7b97c010dd108ba8bb85dd4c37", "html_url": "https://github.com/os6sense/sunra_ffs_relay/commit/35a8b6b3667bda7b97c010dd108ba8bb85dd4c37", "comments_url": "https://api.github.com/repos/os6sense/sunra_ffs_relay/commits/35a8b6b3667bda7b97c010dd108ba8bb85dd4c37/comments", "author": {"login": "os6sense", "id": 934066, "avatar_url": "https://avatars3.githubusercontent.com/u/934066?v=4", "gravatar_id": "", "url": "https://api.github.com/users/os6sense", "html_url": "https://github.com/os6sense", "followers_url": "https://api.github.com/users/os6sense/followers", "following_url": "https://api.github.com/users/os6sense/following{/other_user}", "gists_url": "https://api.github.com/users/os6sense/gists{/gist_id}", "starred_url": "https://api.github.com/users/os6sense/starred{/owner}{/repo}", "subscriptions_url": "https://api.github.com/users/os6sense/subscriptions", "organizations_url": "https://api.github.com/users/os6sense/orgs", "repos_url": "https://api.github.com/users/os6sense/repos", "events_url": "https://api.github.com/users/os6sense/events{/privacy}", "received_events_url": "https://api.github.com/users/os6sense/received_events", "type": "User", "site_admin": false}, "committer": {"login": "os6sense", "id": 934066, "avatar_url": "https://avatars3.githubusercontent.com/u/934066?v=4", "gravatar_id": "", "url": "https://api.github.com/users/os6sense", "html_url": "https://github.com/os6sense", "followers_url": "https://api.github.com/users/os6sense/followers", "following_url": "https://api.github.com/users/os6sense/following{/other_user}", "gists_url": "https://api.github.com/users/os6sense/gists{/gist_id}", "starred_url": "https://api.github.com/users/os6sense/starred{/owner}{/repo}", "subscriptions_url": "https://api.github.com/users/os6sense/subscriptions", "organizations_url": "https://api.github.com/users/os6sense/orgs", "repos_url": "https://api.github.com/users/os6sense/repos", "events_url": "https://api.github.com/users/os6sense/events{/privacy}", "received_events_url": "https://api.github.com/users/os6sense/received_events", "type": "User", "site_admin": false}, "parents": [{"sha": "06a9d7e86906e2870bd4bc2063fd4d39d0bea819", "url": "https://api.github.com/repos/os6sense/sunra_ffs_relay/commits/06a9d7e86906e2870bd4bc2063fd4d39d0bea819", "html_url": "https://github.com/os6sense/sunra_ffs_relay/commit/06a9d7e86906e2870bd4bc2063fd4d39d0bea819"}]}, {"sha": "06a9d7e86906e2870bd4bc2063fd4d39d0bea819", "commit": {"author": {"name": "Lee Jackson", "email": "leej@sowhatresearch.com", "date": "2014-11-03T12:09:30Z"}, "committer": {"name": "Lee Jackson", "email": "leej@sowhatresearch.com", "date": "2014-11-03T12:09:30Z"}, "message": "Renamed the init file", "tree": {"sha": "07cc980567fe4c609b92c3e5f13a19a156da6bca", "url": "https://api.github.com/repos/os6sense/sunra_ffs_relay/git/trees/07cc980567fe4c609b92c3e5f13a19a156da6bca"}, "url": "https://api.github.com/repos/os6sense/sunra_ffs_relay/git/commits/06a9d7e86906e2870bd4bc2063fd4d39d0bea819", "comment_count": 0, "verification": {"verified": false, "reason": "unsigned", "signature": null, "payload": null}}, "url": "https://api.github.com/repos/os6sense/sunra_ffs_relay/commits/06a9d7e86906e2870bd4bc2063fd4d39d0bea819", "html_url": "https://github.com/os6sense/sunra_ffs_relay/commit/06a9d7e86906e2870bd4bc2063fd4d39d0bea819", "comments_url": "https://api.github.com/repos/os6sense/sunra_ffs_relay/commits/06a9d7e86906e2870bd4bc2063fd4d39d0bea819/comments", "author": {"login": "os6sense", "id": 934066, "avatar_url": "https://avatars3.githubusercontent.com/u/934066?v=4", "gravatar_id": "", "url": "https://api.github.com/users/os6sense", "html_url": "https://github.com/os6sense", "followers_url": "https://api.github.com/users/os6sense/followers", "following_url": "https://api.github.com/users/os6sense/following{/other_user}", "gists_url": "https://api.github.com/users/os6sense/gists{/gist_id}", "starred_url": "https://api.github.com/users/os6sense/starred{/owner}{/repo}", "subscriptions_url": "https://api.github.com/users/os6sense/subscriptions", "organizations_url": "https://api.github.com/users/os6sense/orgs", "repos_url": "https://api.github.com/users/os6sense/repos", "events_url": "https://api.github.com/users/os6sense/events{/privacy}", "received_events_url": "https://api.github.com/users/os6sense/received_events", "type": "User", "site_admin": false}, "committer": {"login": "os6sense", "id": 934066, "avatar_url": "https://avatars3.githubusercontent.com/u/934066?v=4", "gravatar_id": "", "url": "https://api.github.com/users/os6sense", "html_url": "https://github.com/os6sense", "followers_url": "https://api.github.com/users/os6sense/followers", "following_url": "https://api.github.com/users/os6sense/following{/other_user}", "gists_url": "https://api.github.com/users/os6sense/gists{/gist_id}", "starred_url": "https://api.github.com/users/os6sense/starred{/owner}{/repo}", "subscriptions_url": "https://api.github.com/users/os6sense/subscriptions", "organizations_url": "https://api.github.com/users/os6sense/orgs", "repos_url": "https://api.github.com/users/os6sense/repos", "events_url": "https://api.github.com/users/os6sense/events{/privacy}", "received_events_url": "https://api.github.com/users/os6sense/received_events", "type": "User", "site_admin": false}, "parents": [{"sha": "cce93bbcab426073c34037fe5b22190c3e053c91", "url": "https://api.github.com/repos/os6sense/sunra_ffs_relay/commits/cce93bbcab426073c34037fe5b22190c3e053c91", "html_url": "https://github.com/os6sense/sunra_ffs_relay/commit/cce93bbcab426073c34037fe5b22190c3e053c91"}]}, {"sha": "cce93bbcab426073c34037fe5b22190c3e053c91", "commit": {"author": {"name": "Lee Jackson", "email": "leej@sowhatresearch.com", "date": "2014-11-03T12:08:50Z"}, "committer": {"name": "Lee Jackson", "email": "leej@sowhatresearch.com", "date": "2014-11-03T12:08:50Z"}, "message": "Updated readme and examples", "tree": {"sha": "fd558892b3f8743e621ecd2337868203bb9d94d4", "url": "https://api.github.com/repos/os6sense/sunra_ffs_relay/git/trees/fd558892b3f8743e621ecd2337868203bb9d94d4"}, "url": "https://api.github.com/repos/os6sense/sunra_ffs_relay/git/commits/cce93bbcab426073c34037fe5b22190c3e053c91", "comment_count": 0, "verification": {"verified": false, "reason": "unsigned", "signature": null, "payload": null}}, "url": "https://api.github.com/repos/os6sense/sunra_ffs_relay/commits/cce93bbcab426073c34037fe5b22190c3e053c91", "html_url": "https://github.com/os6sense/sunra_ffs_relay/commit/cce93bbcab426073c34037fe5b22190c3e053c91", "comments_url": "https://api.github.com/repos/os6sense/sunra_ffs_relay/commits/cce93bbcab426073c34037fe5b22190c3e053c91/comments", "author": {"login": "os6sense", "id": 934066, "avatar_url": "https://avatars3.githubusercontent.com/u/934066?v=4", "gravatar_id": "", "url": "https://api.github.com/users/os6sense", "html_url": "https://github.com/os6sense", "followers_url": "https://api.github.com/users/os6sense/followers", "following_url": "https://api.github.com/users/os6sense/following{/other_user}", "gists_url": "https://api.github.com/users/os6sense/gists{/gist_id}", "starred_url": "https://api.github.com/users/os6sense/starred{/owner}{/repo}", "subscriptions_url": "https://api.github.com/users/os6sense/subscriptions", "organizations_url": "https://api.github.com/users/os6sense/orgs", "repos_url": "https://api.github.com/users/os6sense/repos", "events_url": "https://api.github.com/users/os6sense/events{/privacy}", "received_events_url": "https://api.github.com/users/os6sense/received_events", "type": "User", "site_admin": false}, "committer": {"login": "os6sense", "id": 934066, "avatar_url": "https://avatars3.githubusercontent.com/u/934066?v=4", "gravatar_id": "", "url": "https://api.github.com/users/os6sense", "html_url": "https://github.com/os6sense", "followers_url": "https://api.github.com/users/os6sense/followers", "following_url": "https://api.github.com/users/os6sense/following{/other_user}", "gists_url": "https://api.github.com/users/os6sense/gists{/gist_id}", "starred_url": "https://api.github.com/users/os6sense/starred{/owner}{/repo}", "subscriptions_url": "https://api.github.com/users/os6sense/subscriptions", "organizations_url": "https://api.github.com/users/os6sense/orgs", "repos_url": "https://api.github.com/users/os6sense/repos", "events_url": "https://api.github.com/users/os6sense/events{/privacy}", "received_events_url": "https://api.github.com/users/os6sense/received_events", "type": "User", "site_admin": false}, "parents": [{"sha": "6b4b184583b1fcd81284926c8d072e03f25f173d", "url": "https://api.github.com/repos/os6sense/sunra_ffs_relay/commits/6b4b184583b1fcd81284926c8d072e03f25f173d", "html_url": "https://github.com/os6sense/sunra_ffs_relay/commit/6b4b184583b1fcd81284926c8d072e03f25f173d"}]}, {"sha": "6b4b184583b1fcd81284926c8d072e03f25f173d", "commit": {"author": {"name": "Lee Jackson", "email": "leej@sowhatresearch.com", "date": "2014-11-03T12:05:15Z"}, "committer": {"name": "Lee Jackson", "email": "leej@sowhatresearch.com", "date": "2014-11-03T12:05:15Z"}, "message": "Added the sunra init.d file", "tree": {"sha": "bdc86256ee6ff4f6a41e5162d55cd6f0c8a1313c", "url": "https://api.github.com/repos/os6sense/sunra_ffs_relay/git/trees/bdc86256ee6ff4f6a41e5162d55cd6f0c8a1313c"}, "url": "https://api.github.com/repos/os6sense/sunra_ffs_relay/git/commits/6b4b184583b1fcd81284926c8d072e03f25f173d", "comment_count": 0, "verification": {"verified": false, "reason": "unsigned", "signature": null, "payload": null}}, "url": "https://api.github.com/repos/os6sense/sunra_ffs_relay/commits/6b4b184583b1fcd81284926c8d072e03f25f173d", "html_url": "https://github.com/os6sense/sunra_ffs_relay/commit/6b4b184583b1fcd81284926c8d072e03f25f173d", "comments_url": "https://api.github.com/repos/os6sense/sunra_ffs_relay/commits/6b4b184583b1fcd81284926c8d072e03f25f173d/comments", "author": {"login": "os6sense", "id": 934066, "avatar_url": "https://avatars3.githubusercontent.com/u/934066?v=4", "gravatar_id": "", "url": "https://api.github.com/users/os6sense", "html_url": "https://github.com/os6sense", "followers_url": "https://api.github.com/users/os6sense/followers", "following_url": "https://api.github.com/users/os6sense/following{/other_user}", "gists_url": "https://api.github.com/users/os6sense/gists{/gist_id}", "starred_url": "https://api.github.com/users/os6sense/starred{/owner}{/repo}", "subscriptions_url": "https://api.github.com/users/os6sense/subscriptions", "organizations_url": "https://api.github.com/users/os6sense/orgs", "repos_url": "https://api.github.com/users/os6sense/repos", "events_url": "https://api.github.com/users/os6sense/events{/privacy}", "received_events_url": "https://api.github.com/users/os6sense/received_events", "type": "User", "site_admin": false}, "committer": {"login": "os6sense", "id": 934066, "avatar_url": "https://avatars3.githubusercontent.com/u/934066?v=4", "gravatar_id": "", "url": "https://api.github.com/users/os6sense", "html_url": "https://github.com/os6sense", "followers_url": "https://api.github.com/users/os6sense/followers", "following_url": "https://api.github.com/users/os6sense/following{/other_user}", "gists_url": "https://api.github.com/users/os6sense/gists{/gist_id}", "starred_url": "https://api.github.com/users/os6sense/starred{/owner}{/repo}", "subscriptions_url": "https://api.github.com/users/os6sense/subscriptions", "organizations_url": "https://api.github.com/users/os6sense/orgs", "repos_url": "https://api.github.com/users/os6sense/repos", "events_url": "https://api.github.com/users/os6sense/events{/privacy}", "received_events_url": "https://api.github.com/users/os6sense/received_events", "type": "User", "site_admin": false}, "parents": [{"sha": "6738675b3c8ced37a436baeb0d60a1ca8c19cc79", "url": "https://api.github.com/repos/os6sense/sunra_ffs_relay/commits/6738675b3c8ced37a436baeb0d60a1ca8c19cc79", "html_url": "https://github.com/os6sense/sunra_ffs_relay/commit/6738675b3c8ced37a436baeb0d60a1ca8c19cc79"}]}, {"sha": "6738675b3c8ced37a436baeb0d60a1ca8c19cc79", "commit": {"author": {"name": "Lee Jackson", "email": "leej@sowhatresearch.com", "date": "2014-11-03T11:16:39Z"}, "committer": {"name": "Lee Jackson", "email": "leej@sowhatresearch.com", "date": "2014-11-03T11:16:39Z"}, "message": "Updated readme and examples", "tree": {"sha": "af2e4e7a2f2b250ec21c3a180cfa5c4e63009e18", "url": "https://api.github.com/repos/os6sense/sunra_ffs_relay/git/trees/af2e4e7a2f2b250ec21c3a180cfa5c4e63009e18"}, "url": "https://api.github.com/repos/os6sense/sunra_ffs_relay/git/commits/6738675b3c8ced37a436baeb0d60a1ca8c19cc79", "comment_count": 0, "verification": {"verified": false, "reason": "unsigned", "signature": null, "payload": null}}, "url": "https://api.github.com/repos/os6sense/sunra_ffs_relay/commits/6738675b3c8ced37a436baeb0d60a1ca8c19cc79", "html_url": "https://github.com/os6sense/sunra_ffs_relay/commit/6738675b3c8ced37a436baeb0d60a1ca8c19cc79", "comments_url": "https://api.github.com/repos/os6sense/sunra_ffs_relay/commits/6738675b3c8ced37a436baeb0d60a1ca8c19cc79/comments", "author": {"login": "os6sense", "id": 934066, "avatar_url": "https://avatars3.githubusercontent.com/u/934066?v=4", "gravatar_id": "", "url": "https://api.github.com/users/os6sense", "html_url": "https://github.com/os6sense", "followers_url": "https://api.github.com/users/os6sense/followers", "following_url": "https://api.github.com/users/os6sense/following{/other_user}", "gists_url": "https://api.github.com/users/os6sense/gists{/gist_id}", "starred_url": "https://api.github.com/users/os6sense/starred{/owner}{/repo}", "subscriptions_url": "https://api.github.com/users/os6sense/subscriptions", "organizations_url": "https://api.github.com/users/os6sense/orgs", "repos_url": "https://api.github.com/users/os6sense/repos", "events_url": "https://api.github.com/users/os6sense/events{/privacy}", "received_events_url": "https://api.github.com/users/os6sense/received_events", "type": "User", "site_admin": false}, "committer": {"login": "os6sense", "id": 934066, "avatar_url": "https://avatars3.githubusercontent.com/u/934066?v=4", "gravatar_id": "", "url": "https://api.github.com/users/os6sense", "html_url": "https://github.com/os6sense", "followers_url": "https://api.github.com/users/os6sense/followers", "following_url": "https://api.github.com/users/os6sense/following{/other_user}", "gists_url": "https://api.github.com/users/os6sense/gists{/gist_id}", "starred_url": "https://api.github.com/users/os6sense/starred{/owner}{/repo}", "subscriptions_url": "https://api.github.com/users/os6sense/subscriptions", "organizations_url": "https://api.github.com/users/os6sense/orgs", "repos_url": "https://api.github.com/users/os6sense/repos", "events_url": "https://api.github.com/users/os6sense/events{/privacy}", "received_events_url": "https://api.github.com/users/os6sense/received_events", "type": "User", "site_admin": false}, "parents": [{"sha": "870f7ce447b775bee170e524ac3390342398ea41", "url": "https://api.github.com/repos/os6sense/sunra_ffs_relay/commits/870f7ce447b775bee170e524ac3390342398ea41", "html_url": "https://github.com/os6sense/sunra_ffs_relay/commit/870f7ce447b775bee170e524ac3390342398ea41"}]}, {"sha": "870f7ce447b775bee170e524ac3390342398ea41", "commit": {"author": {"name": "Lee Jackson", "email": "leej@sowhatresearch.com", "date": "2014-11-03T10:47:13Z"}, "committer": {"name": "Lee Jackson", "email": "leej@sowhatresearch.com", "date": "2014-11-03T10:47:13Z"}, "message": "renamed with underscores", "tree": {"sha": "f1048cccaf2d7292b69b88856341179cec35619e", "url": "https://api.github.com/repos/os6sense/sunra_ffs_relay/git/trees/f1048cccaf2d7292b69b88856341179cec35619e"}, "url": "https://api.github.com/repos/os6sense/sunra_ffs_relay/git/commits/870f7ce447b775bee170e524ac3390342398ea41", "comment_count": 0, "verification": {"verified": false, "reason": "unsigned", "signature": null, "payload": null}}, "url": "https://api.github.com/repos/os6sense/sunra_ffs_relay/commits/870f7ce447b775bee170e524ac3390342398ea41", "html_url": "https://github.com/os6sense/sunra_ffs_relay/commit/870f7ce447b775bee170e524ac3390342398ea41", "comments_url": "https://api.github.com/repos/os6sense/sunra_ffs_relay/commits/870f7ce447b775bee170e524ac3390342398ea41/comments", "author": {"login": "os6sense", "id": 934066, "avatar_url": "https://avatars3.githubusercontent.com/u/934066?v=4", "gravatar_id": "", "url": "https://api.github.com/users/os6sense", "html_url": "https://github.com/os6sense", "followers_url": "https://api.github.com/users/os6sense/followers", "following_url": "https://api.github.com/users/os6sense/following{/other_user}", "gists_url": "https://api.github.com/users/os6sense/gists{/gist_id}", "starred_url": "https://api.github.com/users/os6sense/starred{/owner}{/repo}", "subscriptions_url": "https://api.github.com/users/os6sense/subscriptions", "organizations_url": "https://api.github.com/users/os6sense/orgs", "repos_url": "https://api.github.com/users/os6sense/repos", "events_url": "https://api.github.com/users/os6sense/events{/privacy}", "received_events_url": "https://api.github.com/users/os6sense/received_events", "type": "User", "site_admin": false}, "committer": {"login": "os6sense", "id": 934066, "avatar_url": "https://avatars3.githubusercontent.com/u/934066?v=4", "gravatar_id": "", "url": "https://api.github.com/users/os6sense", "html_url": "https://github.com/os6sense", "followers_url": "https://api.github.com/users/os6sense/followers", "following_url": "https://api.github.com/users/os6sense/following{/other_user}", "gists_url": "https://api.github.com/users/os6sense/gists{/gist_id}", "starred_url": "https://api.github.com/users/os6sense/starred{/owner}{/repo}", "subscriptions_url": "https://api.github.com/users/os6sense/subscriptions", "organizations_url": "https://api.github.com/users/os6sense/orgs", "repos_url": "https://api.github.com/users/os6sense/repos", "events_url": "https://api.github.com/users/os6sense/events{/privacy}", "received_events_url": "https://api.github.com/users/os6sense/received_events", "type": "User", "site_admin": false}, "parents": [{"sha": "24bff7d02c23ccb457e66cbb0e59873d8d24ef98", "url": "https://api.github.com/repos/os6sense/sunra_ffs_relay/commits/24bff7d02c23ccb457e66cbb0e59873d8d24ef98", "html_url": "https://github.com/os6sense/sunra_ffs_relay/commit/24bff7d02c23ccb457e66cbb0e59873d8d24ef98"}]}, {"sha": "24bff7d02c23ccb457e66cbb0e59873d8d24ef98", "commit": {"author": {"name": "Lee Jackson", "email": "leej@sowhatresearch.com", "date": "2014-11-03T10:46:24Z"}, "committer": {"name": "Lee Jackson", "email": "leej@sowhatresearch.com", "date": "2014-11-03T10:46:24Z"}, "message": "Style changes", "tree": {"sha": "4478efb4061051c46163244e3059205a682af81b", "url": "https://api.github.com/repos/os6sense/sunra_ffs_relay/git/trees/4478efb4061051c46163244e3059205a682af81b"}, "url": "https://api.github.com/repos/os6sense/sunra_ffs_relay/git/commits/24bff7d02c23ccb457e66cbb0e59873d8d24ef98", "comment_count": 0, "verification": {"verified": false, "reason": "unsigned", "signature": null, "payload": null}}, "url": "https://api.github.com/repos/os6sense/sunra_ffs_relay/commits/24bff7d02c23ccb457e66cbb0e59873d8d24ef98", "html_url": "https://github.com/os6sense/sunra_ffs_relay/commit/24bff7d02c23ccb457e66cbb0e59873d8d24ef98", "comments_url": "https://api.github.com/repos/os6sense/sunra_ffs_relay/commits/24bff7d02c23ccb457e66cbb0e59873d8d24ef98/comments", "author": {"login": "os6sense", "id": 934066, "avatar_url": "https://avatars3.githubusercontent.com/u/934066?v=4", "gravatar_id": "", "url": "https://api.github.com/users/os6sense", "html_url": "https://github.com/os6sense", "followers_url": "https://api.github.com/users/os6sense/followers", "following_url": "https://api.github.com/users/os6sense/following{/other_user}", "gists_url": "https://api.github.com/users/os6sense/gists{/gist_id}", "starred_url": "https://api.github.com/users/os6sense/starred{/owner}{/repo}", "subscriptions_url": "https://api.github.com/users/os6sense/subscriptions", "organizations_url": "https://api.github.com/users/os6sense/orgs", "repos_url": "https://api.github.com/users/os6sense/repos", "events_url": "https://api.github.com/users/os6sense/events{/privacy}", "received_events_url": "https://api.github.com/users/os6sense/received_events", "type": "User", "site_admin": false}, "committer": {"login": "os6sense", "id": 934066, "avatar_url": "https://avatars3.githubusercontent.com/u/934066?v=4", "gravatar_id": "", "url": "https://api.github.com/users/os6sense", "html_url": "https://github.com/os6sense", "followers_url": "https://api.github.com/users/os6sense/followers", "following_url": "https://api.github.com/users/os6sense/following{/other_user}", "gists_url": "https://api.github.com/users/os6sense/gists{/gist_id}", "starred_url": "https://api.github.com/users/os6sense/starred{/owner}{/repo}", "subscriptions_url": "https://api.github.com/users/os6sense/subscriptions", "organizations_url": "https://api.github.com/users/os6sense/orgs", "repos_url": "https://api.github.com/users/os6sense/repos", "events_url": "https://api.github.com/users/os6sense/events{/privacy}", "received_events_url": "https://api.github.com/users/os6sense/received_events", "type": "User", "site_admin": false}, "parents": [{"sha": "90b5e2c1eccafb8f25628579d8a53620eddebf77", "url": "https://api.github.com/repos/os6sense/sunra_ffs_relay/commits/90b5e2c1eccafb8f25628579d8a53620eddebf77", "html_url": "https://github.com/os6sense/sunra_ffs_relay/commit/90b5e2c1eccafb8f25628579d8a53620eddebf77"}]}, {"sha": "90b5e2c1eccafb8f25628579d8a53620eddebf77", "commit": {"author": {"name": "Lee Jackson", "email": "leej@sowhatresearch.com", "date": "2014-11-03T10:46:02Z"}, "committer": {"name": "Lee Jackson", "email": "leej@sowhatresearch.com", "date": "2014-11-03T10:46:02Z"}, "message": "ffmpeg_pipe may be blank OR ommited. Style changes. Renamed", "tree": {"sha": "bc69f75b6cbf20ce03e5533c4866adc601abb997", "url": "https://api.github.com/repos/os6sense/sunra_ffs_relay/git/trees/bc69f75b6cbf20ce03e5533c4866adc601abb997"}, "url": "https://api.github.com/repos/os6sense/sunra_ffs_relay/git/commits/90b5e2c1eccafb8f25628579d8a53620eddebf77", "comment_count": 0, "verification": {"verified": false, "reason": "unsigned", "signature": null, "payload": null}}, "url": "https://api.github.com/repos/os6sense/sunra_ffs_relay/commits/90b5e2c1eccafb8f25628579d8a53620eddebf77", "html_url": "https://github.com/os6sense/sunra_ffs_relay/commit/90b5e2c1eccafb8f25628579d8a53620eddebf77", "comments_url": "https://api.github.com/repos/os6sense/sunra_ffs_relay/commits/90b5e2c1eccafb8f25628579d8a53620eddebf77/comments", "author": {"login": "os6sense", "id": 934066, "avatar_url": "https://avatars3.githubusercontent.com/u/934066?v=4", "gravatar_id": "", "url": "https://api.github.com/users/os6sense", "html_url": "https://github.com/os6sense", "followers_url": "https://api.github.com/users/os6sense/followers", "following_url": "https://api.github.com/users/os6sense/following{/other_user}", "gists_url": "https://api.github.com/users/os6sense/gists{/gist_id}", "starred_url": "https://api.github.com/users/os6sense/starred{/owner}{/repo}", "subscriptions_url": "https://api.github.com/users/os6sense/subscriptions", "organizations_url": "https://api.github.com/users/os6sense/orgs", "repos_url": "https://api.github.com/users/os6sense/repos", "events_url": "https://api.github.com/users/os6sense/events{/privacy}", "received_events_url": "https://api.github.com/users/os6sense/received_events", "type": "User", "site_admin": false}, "committer": {"login": "os6sense", "id": 934066, "avatar_url": "https://avatars3.githubusercontent.com/u/934066?v=4", "gravatar_id": "", "url": "https://api.github.com/users/os6sense", "html_url": "https://github.com/os6sense", "followers_url": "https://api.github.com/users/os6sense/followers", "following_url": "https://api.github.com/users/os6sense/following{/other_user}", "gists_url": "https://api.github.com/users/os6sense/gists{/gist_id}", "starred_url": "https://api.github.com/users/os6sense/starred{/owner}{/repo}", "subscriptions_url": "https://api.github.com/users/os6sense/subscriptions", "organizations_url": "https://api.github.com/users/os6sense/orgs", "repos_url": "https://api.github.com/users/os6sense/repos", "events_url": "https://api.github.com/users/os6sense/events{/privacy}", "received_events_url": "https://api.github.com/users/os6sense/received_events", "type": "User", "site_admin": false}, "parents": [{"sha": "08b79d83c1f1bf96995cdfc6499b1cec335f459a", "url": "https://api.github.com/repos/os6sense/sunra_ffs_relay/commits/08b79d83c1f1bf96995cdfc6499b1cec335f459a", "html_url": "https://github.com/os6sense/sunra_ffs_relay/commit/08b79d83c1f1bf96995cdfc6499b1cec335f459a"}]}, {"sha": "08b79d83c1f1bf96995cdfc6499b1cec335f459a", "commit": {"author": {"name": "Lee Jackson", "email": "leej@sowhatresearch.com", "date": "2014-11-03T10:45:14Z"}, "committer": {"name": "Lee Jackson", "email": "leej@sowhatresearch.com", "date": "2014-11-03T10:45:14Z"}, "message": "Fixed Gemfile to use latest utils; renamed ffserver relay file", "tree": {"sha": "4f7e19fe959d2d3f5ad9e1fa1657ad4fb6cbe175", "url": "https://api.github.com/repos/os6sense/sunra_ffs_relay/git/trees/4f7e19fe959d2d3f5ad9e1fa1657ad4fb6cbe175"}, "url": "https://api.github.com/repos/os6sense/sunra_ffs_relay/git/commits/08b79d83c1f1bf96995cdfc6499b1cec335f459a", "comment_count": 0, "verification": {"verified": false, "reason": "unsigned", "signature": null, "payload": null}}, "url": "https://api.github.com/repos/os6sense/sunra_ffs_relay/commits/08b79d83c1f1bf96995cdfc6499b1cec335f459a", "html_url": "https://github.com/os6sense/sunra_ffs_relay/commit/08b79d83c1f1bf96995cdfc6499b1cec335f459a", "comments_url": "https://api.github.com/repos/os6sense/sunra_ffs_relay/commits/08b79d83c1f1bf96995cdfc6499b1cec335f459a/comments", "author": {"login": "os6sense", "id": 934066, "avatar_url": "https://avatars3.githubusercontent.com/u/934066?v=4", "gravatar_id": "", "url": "https://api.github.com/users/os6sense", "html_url": "https://github.com/os6sense", "followers_url": "https://api.github.com/users/os6sense/followers", "following_url": "https://api.github.com/users/os6sense/following{/other_user}", "gists_url": "https://api.github.com/users/os6sense/gists{/gist_id}", "starred_url": "https://api.github.com/users/os6sense/starred{/owner}{/repo}", "subscriptions_url": "https://api.github.com/users/os6sense/subscriptions", "organizations_url": "https://api.github.com/users/os6sense/orgs", "repos_url": "https://api.github.com/users/os6sense/repos", "events_url": "https://api.github.com/users/os6sense/events{/privacy}", "received_events_url": "https://api.github.com/users/os6sense/received_events", "type": "User", "site_admin": false}, "committer": {"login": "os6sense", "id": 934066, "avatar_url": "https://avatars3.githubusercontent.com/u/934066?v=4", "gravatar_id": "", "url": "https://api.github.com/users/os6sense", "html_url": "https://github.com/os6sense", "followers_url": "https://api.github.com/users/os6sense/followers", "following_url": "https://api.github.com/users/os6sense/following{/other_user}", "gists_url": "https://api.github.com/users/os6sense/gists{/gist_id}", "starred_url": "https://api.github.com/users/os6sense/starred{/owner}{/repo}", "subscriptions_url": "https://api.github.com/users/os6sense/subscriptions", "organizations_url": "https://api.github.com/users/os6sense/orgs", "repos_url": "https://api.github.com/users/os6sense/repos", "events_url": "https://api.github.com/users/os6sense/events{/privacy}", "received_events_url": "https://api.github.com/users/os6sense/received_events", "type": "User", "site_admin": false}, "parents": [{"sha": "8839fe921ecf6a324b98a2ed06c57e463a46a8d8", "url": "https://api.github.com/repos/os6sense/sunra_ffs_relay/commits/8839fe921ecf6a324b98a2ed06c57e463a46a8d8", "html_url": "https://github.com/os6sense/sunra_ffs_relay/commit/8839fe921ecf6a324b98a2ed06c57e463a46a8d8"}]}, {"sha": "8839fe921ecf6a324b98a2ed06c57e463a46a8d8", "commit": {"author": {"name": "os6sense", "email": "leej@sowhatresearch.com", "date": "2014-09-24T18:30:17Z"}, "committer": {"name": "os6sense", "email": "leej@sowhatresearch.com", "date": "2014-09-24T18:30:17Z"}, "message": "Style issues", "tree": {"sha": "4d46e3d4b2a5627627983a02d2e1f4bac54fd98a", "url": "https://api.github.com/repos/os6sense/sunra_ffs_relay/git/trees/4d46e3d4b2a5627627983a02d2e1f4bac54fd98a"}, "url": "https://api.github.com/repos/os6sense/sunra_ffs_relay/git/commits/8839fe921ecf6a324b98a2ed06c57e463a46a8d8", "comment_count": 0, "verification": {"verified": false, "reason": "unsigned", "signature": null, "payload": null}}, "url": "https://api.github.com/repos/os6sense/sunra_ffs_relay/commits/8839fe921ecf6a324b98a2ed06c57e463a46a8d8", "html_url": "https://github.com/os6sense/sunra_ffs_relay/commit/8839fe921ecf6a324b98a2ed06c57e463a46a8d8", "comments_url": "https://api.github.com/repos/os6sense/sunra_ffs_relay/commits/8839fe921ecf6a324b98a2ed06c57e463a46a8d8/comments", "author": {"login": "os6sense", "id": 934066, "avatar_url": "https://avatars3.githubusercontent.com/u/934066?v=4", "gravatar_id": "", "url": "https://api.github.com/users/os6sense", "html_url": "https://github.com/os6sense", "followers_url": "https://api.github.com/users/os6sense/followers", "following_url": "https://api.github.com/users/os6sense/following{/other_user}", "gists_url": "https://api.github.com/users/os6sense/gists{/gist_id}", "starred_url": "https://api.github.com/users/os6sense/starred{/owner}{/repo}", "subscriptions_url": "https://api.github.com/users/os6sense/subscriptions", "organizations_url": "https://api.github.com/users/os6sense/orgs", "repos_url": "https://api.github.com/users/os6sense/repos", "events_url": "https://api.github.com/users/os6sense/events{/privacy}", "received_events_url": "https://api.github.com/users/os6sense/received_events", "type": "User", "site_admin": false}, "committer": {"login": "os6sense", "id": 934066, "avatar_url": "https://avatars3.githubusercontent.com/u/934066?v=4", "gravatar_id": "", "url": "https://api.github.com/users/os6sense", "html_url": "https://github.com/os6sense", "followers_url": "https://api.github.com/users/os6sense/followers", "following_url": "https://api.github.com/users/os6sense/following{/other_user}", "gists_url": "https://api.github.com/users/os6sense/gists{/gist_id}", "starred_url": "https://api.github.com/users/os6sense/starred{/owner}{/repo}", "subscriptions_url": "https://api.github.com/users/os6sense/subscriptions", "organizations_url": "https://api.github.com/users/os6sense/orgs", "repos_url": "https://api.github.com/users/os6sense/repos", "events_url": "https://api.github.com/users/os6sense/events{/privacy}", "received_events_url": "https://api.github.com/users/os6sense/received_events", "type": "User", "site_admin": false}, "parents": [{"sha": "a001cb70117f1f95416a06c42c5b87017e3b0949", "url": "https://api.github.com/repos/os6sense/sunra_ffs_relay/commits/a001cb70117f1f95416a06c42c5b87017e3b0949", "html_url": "https://github.com/os6sense/sunra_ffs_relay/commit/a001cb70117f1f95416a06c42c5b87017e3b0949"}]}, {"sha": "a001cb70117f1f95416a06c42c5b87017e3b0949", "commit": {"author": {"name": "os6sense", "email": "leej@sowhatresearch.com", "date": "2014-09-24T18:26:23Z"}, "committer": {"name": "os6sense", "email": "leej@sowhatresearch.com", "date": "2014-09-24T18:26:23Z"}, "message": "travis added", "tree": {"sha": "2ca5e6f40e695b1c9659033e6ee3baee390d76a1", "url": "https://api.github.com/repos/os6sense/sunra_ffs_relay/git/trees/2ca5e6f40e695b1c9659033e6ee3baee390d76a1"}, "url": "https://api.github.com/repos/os6sense/sunra_ffs_relay/git/commits/a001cb70117f1f95416a06c42c5b87017e3b0949", "comment_count": 0, "verification": {"verified": false, "reason": "unsigned", "signature": null, "payload": null}}, "url": "https://api.github.com/repos/os6sense/sunra_ffs_relay/commits/a001cb70117f1f95416a06c42c5b87017e3b0949", "html_url": "https://github.com/os6sense/sunra_ffs_relay/commit/a001cb70117f1f95416a06c42c5b87017e3b0949", "comments_url": "https://api.github.com/repos/os6sense/sunra_ffs_relay/commits/a001cb70117f1f95416a06c42c5b87017e3b0949/comments", "author": {"login": "os6sense", "id": 934066, "avatar_url": "https://avatars3.githubusercontent.com/u/934066?v=4", "gravatar_id": "", "url": "https://api.github.com/users/os6sense", "html_url": "https://github.com/os6sense", "followers_url": "https://api.github.com/users/os6sense/followers", "following_url": "https://api.github.com/users/os6sense/following{/other_user}", "gists_url": "https://api.github.com/users/os6sense/gists{/gist_id}", "starred_url": "https://api.github.com/users/os6sense/starred{/owner}{/repo}", "subscriptions_url": "https://api.github.com/users/os6sense/subscriptions", "organizations_url": "https://api.github.com/users/os6sense/orgs", "repos_url": "https://api.github.com/users/os6sense/repos", "events_url": "https://api.github.com/users/os6sense/events{/privacy}", "received_events_url": "https://api.github.com/users/os6sense/received_events", "type": "User", "site_admin": false}, "committer": {"login": "os6sense", "id": 934066, "avatar_url": "https://avatars3.githubusercontent.com/u/934066?v=4", "gravatar_id": "", "url": "https://api.github.com/users/os6sense", "html_url": "https://github.com/os6sense", "followers_url": "https://api.github.com/users/os6sense/followers", "following_url": "https://api.github.com/users/os6sense/following{/other_user}", "gists_url": "https://api.github.com/users/os6sense/gists{/gist_id}", "starred_url": "https://api.github.com/users/os6sense/starred{/owner}{/repo}", "subscriptions_url": "https://api.github.com/users/os6sense/subscriptions", "organizations_url": "https://api.github.com/users/os6sense/orgs", "repos_url": "https://api.github.com/users/os6sense/repos", "events_url": "https://api.github.com/users/os6sense/events{/privacy}", "received_events_url": "https://api.github.com/users/os6sense/received_events", "type": "User", "site_admin": false}, "parents": [{"sha": "0ea3a6071ada8c6cc946da7a658438b27c3999ee", "url": "https://api.github.com/repos/os6sense/sunra_ffs_relay/commits/0ea3a6071ada8c6cc946da7a658438b27c3999ee", "html_url": "https://github.com/os6sense/sunra_ffs_relay/commit/0ea3a6071ada8c6cc946da7a658438b27c3999ee"}]}, {"sha": "0ea3a6071ada8c6cc946da7a658438b27c3999ee", "commit": {"author": {"name": "os6sense", "email": "leej@sowhatresearch.com", "date": "2014-09-22T18:50:53Z"}, "committer": {"name": "os6sense", "email": "leej@sowhatresearch.com", "date": "2014-09-22T18:50:53Z"}, "message": "README and LICENSE", "tree": {"sha": "a575397efd53712540515919502dfaae7c67e517", "url": "https://api.github.com/repos/os6sense/sunra_ffs_relay/git/trees/a575397efd53712540515919502dfaae7c67e517"}, "url": "https://api.github.com/repos/os6sense/sunra_ffs_relay/git/commits/0ea3a6071ada8c6cc946da7a658438b27c3999ee", "comment_count": 0, "verification": {"verified": false, "reason": "unsigned", "signature": null, "payload": null}}, "url": "https://api.github.com/repos/os6sense/sunra_ffs_relay/commits/0ea3a6071ada8c6cc946da7a658438b27c3999ee", "html_url": "https://github.com/os6sense/sunra_ffs_relay/commit/0ea3a6071ada8c6cc946da7a658438b27c3999ee", "comments_url": "https://api.github.com/repos/os6sense/sunra_ffs_relay/commits/0ea3a6071ada8c6cc946da7a658438b27c3999ee/comments", "author": {"login": "os6sense", "id": 934066, "avatar_url": "https://avatars3.githubusercontent.com/u/934066?v=4", "gravatar_id": "", "url": "https://api.github.com/users/os6sense", "html_url": "https://github.com/os6sense", "followers_url": "https://api.github.com/users/os6sense/followers", "following_url": "https://api.github.com/users/os6sense/following{/other_user}", "gists_url": "https://api.github.com/users/os6sense/gists{/gist_id}", "starred_url": "https://api.github.com/users/os6sense/starred{/owner}{/repo}", "subscriptions_url": "https://api.github.com/users/os6sense/subscriptions", "organizations_url": "https://api.github.com/users/os6sense/orgs", "repos_url": "https://api.github.com/users/os6sense/repos", "events_url": "https://api.github.com/users/os6sense/events{/privacy}", "received_events_url": "https://api.github.com/users/os6sense/received_events", "type": "User", "site_admin": false}, "committer": {"login": "os6sense", "id": 934066, "avatar_url": "https://avatars3.githubusercontent.com/u/934066?v=4", "gravatar_id": "", "url": "https://api.github.com/users/os6sense", "html_url": "https://github.com/os6sense", "followers_url": "https://api.github.com/users/os6sense/followers", "following_url": "https://api.github.com/users/os6sense/following{/other_user}", "gists_url": "https://api.github.com/users/os6sense/gists{/gist_id}", "starred_url": "https://api.github.com/users/os6sense/starred{/owner}{/repo}", "subscriptions_url": "https://api.github.com/users/os6sense/subscriptions", "organizations_url": "https://api.github.com/users/os6sense/orgs", "repos_url": "https://api.github.com/users/os6sense/repos", "events_url": "https://api.github.com/users/os6sense/events{/privacy}", "received_events_url": "https://api.github.com/users/os6sense/received_events", "type": "User", "site_admin": false}, "parents": [{"sha": "d1a7c4592b5349de0add513c001bc9a8c324158c", "url": "https://api.github.com/repos/os6sense/sunra_ffs_relay/commits/d1a7c4592b5349de0add513c001bc9a8c324158c", "html_url": "https://github.com/os6sense/sunra_ffs_relay/commit/d1a7c4592b5349de0add513c001bc9a8c324158c"}]}, {"sha": "d1a7c4592b5349de0add513c001bc9a8c324158c", "commit": {"author": {"name": "os6sense", "email": "leej@sowhatresearch.com", "date": "2014-09-22T18:50:22Z"}, "committer": {"name": "os6sense", "email": "leej@sowhatresearch.com", "date": "2014-09-22T18:50:22Z"}, "message": "README and LICENSE", "tree": {"sha": "f0d90bc64b672a0513a9cf1ccc0e34f5f517a4a1", "url": "https://api.github.com/repos/os6sense/sunra_ffs_relay/git/trees/f0d90bc64b672a0513a9cf1ccc0e34f5f517a4a1"}, "url": "https://api.github.com/repos/os6sense/sunra_ffs_relay/git/commits/d1a7c4592b5349de0add513c001bc9a8c324158c", "comment_count": 0, "verification": {"verified": false, "reason": "unsigned", "signature": null, "payload": null}}, "url": "https://api.github.com/repos/os6sense/sunra_ffs_relay/commits/d1a7c4592b5349de0add513c001bc9a8c324158c", "html_url": "https://github.com/os6sense/sunra_ffs_relay/commit/d1a7c4592b5349de0add513c001bc9a8c324158c", "comments_url": "https://api.github.com/repos/os6sense/sunra_ffs_relay/commits/d1a7c4592b5349de0add513c001bc9a8c324158c/comments", "author": {"login": "os6sense", "id": 934066, "avatar_url": "https://avatars3.githubusercontent.com/u/934066?v=4", "gravatar_id": "", "url": "https://api.github.com/users/os6sense", "html_url": "https://github.com/os6sense", "followers_url": "https://api.github.com/users/os6sense/followers", "following_url": "https://api.github.com/users/os6sense/following{/other_user}", "gists_url": "https://api.github.com/users/os6sense/gists{/gist_id}", "starred_url": "https://api.github.com/users/os6sense/starred{/owner}{/repo}", "subscriptions_url": "https://api.github.com/users/os6sense/subscriptions", "organizations_url": "https://api.github.com/users/os6sense/orgs", "repos_url": "https://api.github.com/users/os6sense/repos", "events_url": "https://api.github.com/users/os6sense/events{/privacy}", "received_events_url": "https://api.github.com/users/os6sense/received_events", "type": "User", "site_admin": false}, "committer": {"login": "os6sense", "id": 934066, "avatar_url": "https://avatars3.githubusercontent.com/u/934066?v=4", "gravatar_id": "", "url": "https://api.github.com/users/os6sense", "html_url": "https://github.com/os6sense", "followers_url": "https://api.github.com/users/os6sense/followers", "following_url": "https://api.github.com/users/os6sense/following{/other_user}", "gists_url": "https://api.github.com/users/os6sense/gists{/gist_id}", "starred_url": "https://api.github.com/users/os6sense/starred{/owner}{/repo}", "subscriptions_url": "https://api.github.com/users/os6sense/subscriptions", "organizations_url": "https://api.github.com/users/os6sense/orgs", "repos_url": "https://api.github.com/users/os6sense/repos", "events_url": "https://api.github.com/users/os6sense/events{/privacy}", "received_events_url": "https://api.github.com/users/os6sense/received_events", "type": "User", "site_admin": false}, "parents": [{"sha": "5cb84453081f39c4b030da8589fc79dc50d2082b", "url": "https://api.github.com/repos/os6sense/sunra_ffs_relay/commits/5cb84453081f39c4b030da8589fc79dc50d2082b", "html_url": "https://github.com/os6sense/sunra_ffs_relay/commit/5cb84453081f39c4b030da8589fc79dc50d2082b"}]}, {"sha": "5cb84453081f39c4b030da8589fc79dc50d2082b", "commit": {"author": {"name": "os6sense", "email": "leej@sowhatresearch.com", "date": "2014-09-22T18:47:08Z"}, "committer": {"name": "os6sense", "email": "leej@sowhatresearch.com", "date": "2014-09-22T18:47:08Z"}, "message": "Reorganisation to allow for sunra_utils gem. Tidy up", "tree": {"sha": "15bbad57b9ee925fe150b635170d2822750e6dca", "url": "https://api.github.com/repos/os6sense/sunra_ffs_relay/git/trees/15bbad57b9ee925fe150b635170d2822750e6dca"}, "url": "https://api.github.com/repos/os6sense/sunra_ffs_relay/git/commits/5cb84453081f39c4b030da8589fc79dc50d2082b", "comment_count": 0, "verification": {"verified": false, "reason": "unsigned", "signature": null, "payload": null}}, "url": "https://api.github.com/repos/os6sense/sunra_ffs_relay/commits/5cb84453081f39c4b030da8589fc79dc50d2082b", "html_url": "https://github.com/os6sense/sunra_ffs_relay/commit/5cb84453081f39c4b030da8589fc79dc50d2082b", "comments_url": "https://api.github.com/repos/os6sense/sunra_ffs_relay/commits/5cb84453081f39c4b030da8589fc79dc50d2082b/comments", "author": {"login": "os6sense", "id": 934066, "avatar_url": "https://avatars3.githubusercontent.com/u/934066?v=4", "gravatar_id": "", "url": "https://api.github.com/users/os6sense", "html_url": "https://github.com/os6sense", "followers_url": "https://api.github.com/users/os6sense/followers", "following_url": "https://api.github.com/users/os6sense/following{/other_user}", "gists_url": "https://api.github.com/users/os6sense/gists{/gist_id}", "starred_url": "https://api.github.com/users/os6sense/starred{/owner}{/repo}", "subscriptions_url": "https://api.github.com/users/os6sense/subscriptions", "organizations_url": "https://api.github.com/users/os6sense/orgs", "repos_url": "https://api.github.com/users/os6sense/repos", "events_url": "https://api.github.com/users/os6sense/events{/privacy}", "received_events_url": "https://api.github.com/users/os6sense/received_events", "type": "User", "site_admin": false}, "committer": {"login": "os6sense", "id": 934066, "avatar_url": "https://avatars3.githubusercontent.com/u/934066?v=4", "gravatar_id": "", "url": "https://api.github.com/users/os6sense", "html_url": "https://github.com/os6sense", "followers_url": "https://api.github.com/users/os6sense/followers", "following_url": "https://api.github.com/users/os6sense/following{/other_user}", "gists_url": "https://api.github.com/users/os6sense/gists{/gist_id}", "starred_url": "https://api.github.com/users/os6sense/starred{/owner}{/repo}", "subscriptions_url": "https://api.github.com/users/os6sense/subscriptions", "organizations_url": "https://api.github.com/users/os6sense/orgs", "repos_url": "https://api.github.com/users/os6sense/repos", "events_url": "https://api.github.com/users/os6sense/events{/privacy}", "received_events_url": "https://api.github.com/users/os6sense/received_events", "type": "User", "site_admin": false}, "parents": [{"sha": "ac0542d5283f3f49800709924c2ecfe2455f0086", "url": "https://api.github.com/repos/os6sense/sunra_ffs_relay/commits/ac0542d5283f3f49800709924c2ecfe2455f0086", "html_url": "https://github.com/os6sense/sunra_ffs_relay/commit/ac0542d5283f3f49800709924c2ecfe2455f0086"}]}, {"sha": "ac0542d5283f3f49800709924c2ecfe2455f0086", "commit": {"author": {"name": "os6sense", "email": "leej@sowhatresearch.com", "date": "2014-09-22T18:20:40Z"}, "committer": {"name": "os6sense", "email": "leej@sowhatresearch.com", "date": "2014-09-22T18:20:40Z"}, "message": "About to refactor to use new utils collection", "tree": {"sha": "d8605ddc943c717e0dd7eb85dbf756a2e912da97", "url": "https://api.github.com/repos/os6sense/sunra_ffs_relay/git/trees/d8605ddc943c717e0dd7eb85dbf756a2e912da97"}, "url": "https://api.github.com/repos/os6sense/sunra_ffs_relay/git/commits/ac0542d5283f3f49800709924c2ecfe2455f0086", "comment_count": 0, "verification": {"verified": false, "reason": "unsigned", "signature": null, "payload": null}}, "url": "https://api.github.com/repos/os6sense/sunra_ffs_relay/commits/ac0542d5283f3f49800709924c2ecfe2455f0086", "html_url": "https://github.com/os6sense/sunra_ffs_relay/commit/ac0542d5283f3f49800709924c2ecfe2455f0086", "comments_url": "https://api.github.com/repos/os6sense/sunra_ffs_relay/commits/ac0542d5283f3f49800709924c2ecfe2455f0086/comments", "author": {"login": "os6sense", "id": 934066, "avatar_url": "https://avatars3.githubusercontent.com/u/934066?v=4", "gravatar_id": "", "url": "https://api.github.com/users/os6sense", "html_url": "https://github.com/os6sense", "followers_url": "https://api.github.com/users/os6sense/followers", "following_url": "https://api.github.com/users/os6sense/following{/other_user}", "gists_url": "https://api.github.com/users/os6sense/gists{/gist_id}", "starred_url": "https://api.github.com/users/os6sense/starred{/owner}{/repo}", "subscriptions_url": "https://api.github.com/users/os6sense/subscriptions", "organizations_url": "https://api.github.com/users/os6sense/orgs", "repos_url": "https://api.github.com/users/os6sense/repos", "events_url": "https://api.github.com/users/os6sense/events{/privacy}", "received_events_url": "https://api.github.com/users/os6sense/received_events", "type": "User", "site_admin": false}, "committer": {"login": "os6sense", "id": 934066, "avatar_url": "https://avatars3.githubusercontent.com/u/934066?v=4", "gravatar_id": "", "url": "https://api.github.com/users/os6sense", "html_url": "https://github.com/os6sense", "followers_url": "https://api.github.com/users/os6sense/followers", "following_url": "https://api.github.com/users/os6sense/following{/other_user}", "gists_url": "https://api.github.com/users/os6sense/gists{/gist_id}", "starred_url": "https://api.github.com/users/os6sense/starred{/owner}{/repo}", "subscriptions_url": "https://api.github.com/users/os6sense/subscriptions", "organizations_url": "https://api.github.com/users/os6sense/orgs", "repos_url": "https://api.github.com/users/os6sense/repos", "events_url": "https://api.github.com/users/os6sense/events{/privacy}", "received_events_url": "https://api.github.com/users/os6sense/received_events", "type": "User", "site_admin": false}, "parents": [{"sha": "c1a71488cde66d0ec2500a1fa5da97d5b6416f88", "url": "https://api.github.com/repos/os6sense/sunra_ffs_relay/commits/c1a71488cde66d0ec2500a1fa5da97d5b6416f88", "html_url": "https://github.com/os6sense/sunra_ffs_relay/commit/c1a71488cde66d0ec2500a1fa5da97d5b6416f88"}]}, {"sha": "c1a71488cde66d0ec2500a1fa5da97d5b6416f88", "commit": {"author": {"name": "os6sense", "email": "leej@sowhatresearch.com", "date": "2014-09-22T09:42:30Z"}, "committer": {"name": "os6sense", "email": "leej@sowhatresearch.com", "date": "2014-09-22T09:42:30Z"}, "message": "Updated service namespace", "tree": {"sha": "bbc4e312c16d9df0e9fc927587b11730912e99d9", "url": "https://api.github.com/repos/os6sense/sunra_ffs_relay/git/trees/bbc4e312c16d9df0e9fc927587b11730912e99d9"}, "url": "https://api.github.com/repos/os6sense/sunra_ffs_relay/git/commits/c1a71488cde66d0ec2500a1fa5da97d5b6416f88", "comment_count": 0, "verification": {"verified": false, "reason": "unsigned", "signature": null, "payload": null}}, "url": "https://api.github.com/repos/os6sense/sunra_ffs_relay/commits/c1a71488cde66d0ec2500a1fa5da97d5b6416f88", "html_url": "https://github.com/os6sense/sunra_ffs_relay/commit/c1a71488cde66d0ec2500a1fa5da97d5b6416f88", "comments_url": "https://api.github.com/repos/os6sense/sunra_ffs_relay/commits/c1a71488cde66d0ec2500a1fa5da97d5b6416f88/comments", "author": {"login": "os6sense", "id": 934066, "avatar_url": "https://avatars3.githubusercontent.com/u/934066?v=4", "gravatar_id": "", "url": "https://api.github.com/users/os6sense", "html_url": "https://github.com/os6sense", "followers_url": "https://api.github.com/users/os6sense/followers", "following_url": "https://api.github.com/users/os6sense/following{/other_user}", "gists_url": "https://api.github.com/users/os6sense/gists{/gist_id}", "starred_url": "https://api.github.com/users/os6sense/starred{/owner}{/repo}", "subscriptions_url": "https://api.github.com/users/os6sense/subscriptions", "organizations_url": "https://api.github.com/users/os6sense/orgs", "repos_url": "https://api.github.com/users/os6sense/repos", "events_url": "https://api.github.com/users/os6sense/events{/privacy}", "received_events_url": "https://api.github.com/users/os6sense/received_events", "type": "User", "site_admin": false}, "committer": {"login": "os6sense", "id": 934066, "avatar_url": "https://avatars3.githubusercontent.com/u/934066?v=4", "gravatar_id": "", "url": "https://api.github.com/users/os6sense", "html_url": "https://github.com/os6sense", "followers_url": "https://api.github.com/users/os6sense/followers", "following_url": "https://api.github.com/users/os6sense/following{/other_user}", "gists_url": "https://api.github.com/users/os6sense/gists{/gist_id}", "starred_url": "https://api.github.com/users/os6sense/starred{/owner}{/repo}", "subscriptions_url": "https://api.github.com/users/os6sense/subscriptions", "organizations_url": "https://api.github.com/users/os6sense/orgs", "repos_url": "https://api.github.com/users/os6sense/repos", "events_url": "https://api.github.com/users/os6sense/events{/privacy}", "received_events_url": "https://api.github.com/users/os6sense/received_events", "type": "User", "site_admin": false}, "parents": [{"sha": "63ac6728b3557daf39a283f45be819fa033ec66d", "url": "https://api.github.com/repos/os6sense/sunra_ffs_relay/commits/63ac6728b3557daf39a283f45be819fa033ec66d", "html_url": "https://github.com/os6sense/sunra_ffs_relay/commit/63ac6728b3557daf39a283f45be819fa033ec66d"}]}, {"sha": "63ac6728b3557daf39a283f45be819fa033ec66d", "commit": {"author": {"name": "os6sense", "email": "leej@sowhatresearch.com", "date": "2014-09-10T20:26:22Z"}, "committer": {"name": "os6sense", "email": "leej@sowhatresearch.com", "date": "2014-09-10T20:26:22Z"}, "message": "First commit as a submodule", "tree": {"sha": "9c10cf5909a7f12ec697176cf612aa46d4e3f2b9", "url": "https://api.github.com/repos/os6sense/sunra_ffs_relay/git/trees/9c10cf5909a7f12ec697176cf612aa46d4e3f2b9"}, "url": "https://api.github.com/repos/os6sense/sunra_ffs_relay/git/commits/63ac6728b3557daf39a283f45be819fa033ec66d", "comment_count": 0, "verification": {"verified": false, "reason": "unsigned", "signature": null, "payload": null}}, "url": "https://api.github.com/repos/os6sense/sunra_ffs_relay/commits/63ac6728b3557daf39a283f45be819fa033ec66d", "html_url": "https://github.com/os6sense/sunra_ffs_relay/commit/63ac6728b3557daf39a283f45be819fa033ec66d", "comments_url": "https://api.github.com/repos/os6sense/sunra_ffs_relay/commits/63ac6728b3557daf39a283f45be819fa033ec66d/comments", "author": {"login": "os6sense", "id": 934066, "avatar_url": "https://avatars3.githubusercontent.com/u/934066?v=4", "gravatar_id": "", "url": "https://api.github.com/users/os6sense", "html_url": "https://github.com/os6sense", "followers_url": "https://api.github.com/users/os6sense/followers", "following_url": "https://api.github.com/users/os6sense/following{/other_user}", "gists_url": "https://api.github.com/users/os6sense/gists{/gist_id}", "starred_url": "https://api.github.com/users/os6sense/starred{/owner}{/repo}", "subscriptions_url": "https://api.github.com/users/os6sense/subscriptions", "organizations_url": "https://api.github.com/users/os6sense/orgs", "repos_url": "https://api.github.com/users/os6sense/repos", "events_url": "https://api.github.com/users/os6sense/events{/privacy}", "received_events_url": "https://api.github.com/users/os6sense/received_events", "type": "User", "site_admin": false}, "committer": {"login": "os6sense", "id": 934066, "avatar_url": "https://avatars3.githubusercontent.com/u/934066?v=4", "gravatar_id": "", "url": "https://api.github.com/users/os6sense", "html_url": "https://github.com/os6sense", "followers_url": "https://api.github.com/users/os6sense/followers", "following_url": "https://api.github.com/users/os6sense/following{/other_user}", "gists_url": "https://api.github.com/users/os6sense/gists{/gist_id}", "starred_url": "https://api.github.com/users/os6sense/starred{/owner}{/repo}", "subscriptions_url": "https://api.github.com/users/os6sense/subscriptions", "organizations_url": "https://api.github.com/users/os6sense/orgs", "repos_url": "https://api.github.com/users/os6sense/repos", "events_url": "https://api.github.com/users/os6sense/events{/privacy}", "received_events_url": "https://api.github.com/users/os6sense/received_events", "type": "User", "site_admin": false}, "parents": []}], "pull_requests": [], "issue_comments": [{"url": "https://api.github.com/repos/os6sense/sunra_ffs_relay/issues/comments/88483093", "html_url": "https://github.com/os6sense/sunra_ffs_relay/issues/2#issuecomment-88483093", "issue_url": "https://api.github.com/repos/os6sense/sunra_ffs_relay/issues/2", "id": 88483093, "user": {"login": "os6sense", "id": 934066, "avatar_url": "https://avatars3.githubusercontent.com/u/934066?v=4", "gravatar_id": "", "url": "https://api.github.com/users/os6sense", "html_url": "https://github.com/os6sense", "followers_url": "https://api.github.com/users/os6sense/followers", "following_url": "https://api.github.com/users/os6sense/following{/other_user}", "gists_url": "https://api.github.com/users/os6sense/gists{/gist_id}", "starred_url": "https://api.github.com/users/os6sense/starred{/owner}{/repo}", "subscriptions_url": "https://api.github.com/users/os6sense/subscriptions", "organizations_url": "https://api.github.com/users/os6sense/orgs", "repos_url": "https://api.github.com/users/os6sense/repos", "events_url": "https://api.github.com/users/os6sense/events{/privacy}", "received_events_url": "https://api.github.com/users/os6sense/received_events", "type": "User", "site_admin": false}, "created_at": "2015-04-01T13:36:16Z", "updated_at": "2015-04-01T13:36:16Z", "author_association": "OWNER", "body": "Looks like an issue with get_pid in sunra_utils\n", "reactions": {"url": "https://api.github.com/repos/os6sense/sunra_ffs_relay/issues/comments/88483093/reactions", "total_count": 0, "+1": 0, "-1": 0, "laugh": 0, "hooray": 0, "confused": 0, "heart": 0}}], "commit_comments": [], "review_comments": []}}}